{
  "id": "espn:5573",
  "fantasy": {
    "id": "espn:5573",
    "name": "Dontarrious Thomas",
    "position": null,
    "team": null,
    "identifiers": {
      "sleeper_id": null,
      "espn_id": "5573",
      "gsis_id": null
    },
    "height": null,
    "weight": null,
    "college": null,
    "age": null,
    "years_exp": null,
    "birth_date": null
  },
  "nfl": {
    "bio": {
      "gsis_id": "00-0022917",
      "display_name": "Dontarrious Thomas",
      "common_first_name": "Dontarrious",
      "first_name": "Dontarrious",
      "last_name": "Thomas",
      "short_name": null,
      "football_name": null,
      "suffix": null,
      "esb_id": "THO116693",
      "nfl_id": "29001",
      "pfr_id": "ThomDo21",
      "pff_id": "1769",
      "otc_id": null,
      "espn_id": "5573",
      "smart_id": "32005448-4f11-6693-e28e-fd4ddf4e6f0f",
      "birth_date": "1980-09-02",
      "position_group": "LB",
      "position": "LB",
      "ngs_position_group": null,
      "ngs_position": null,
      "height": 74.0,
      "weight": 241.0,
      "headshot": "https://static.www.nfl.com/image/private/f_auto,q_auto/league/bqijd5kq7txeankg0jai",
      "college_name": "Auburn",
      "college_conference": null,
      "jersey_number": "57",
      "rookie_season": 2004,
      "last_season": 2009,
      "latest_team": "LAC",
      "status": "ACT",
      "ngs_status": null,
      "ngs_status_short_description": null,
      "years_of_experience": 6,
      "pff_position": null,
      "pff_status": null,
      "draft_year": 2004.0,
      "draft_round": 2.0,
      "draft_pick": 48.0,
      "draft_team": "MIN"
    },
    "stats": [],
    "sportradar": {}
  }
}