{
  "id": "espn:1533",
  "fantasy": {
    "id": "espn:1533",
    "name": "Benji Olson",
    "position": null,
    "team": null,
    "identifiers": {
      "sleeper_id": null,
      "espn_id": "1533",
      "gsis_id": null
    },
    "height": null,
    "weight": null,
    "college": null,
    "age": null,
    "years_exp": null,
    "birth_date": null
  },
  "nfl": {
    "bio": {
      "gsis_id": "00-0012381",
      "display_name": "Benji Olson",
      "common_first_name": "Benji",
      "first_name": "Benjamin",
      "last_name": "Olson",
      "short_name": null,
      "football_name": null,
      "suffix": null,
      "esb_id": "OLS351377",
      "nfl_id": "23586",
      "pfr_id": "OlsoBe20",
      "pff_id": "397",
      "otc_id": null,
      "espn_id": "1533",
      "smart_id": "32004f4c-5335-1377-cfac-0b25247eef56",
      "birth_date": "1975-06-05",
      "position_group": "OL",
      "position": "G",
      "ngs_position_group": null,
      "ngs_position": null,
      "height": 76.0,
      "weight": 320.0,
      "headshot": "https://static.www.nfl.com/image/private/f_auto,q_auto/league/ycrpvvvlmrkt6hqkv706",
      "college_name": "Washington",
      "college_conference": null,
      "jersey_number": "75",
      "rookie_season": 1998,
      "last_season": 2007,
      "latest_team": "TEN",
      "status": "ACT",
      "ngs_status": null,
      "ngs_status_short_description": null,
      "years_of_experience": 10,
      "pff_position": null,
      "pff_status": null,
      "draft_year": 1998.0,
      "draft_round": 5.0,
      "draft_pick": 139.0,
      "draft_team": "TEN"
    },
    "stats": [],
    "sportradar": {}
  }
}