{
  "id": "espn:7459",
  "fantasy": {
    "id": "espn:7459",
    "name": "Thomas Homco",
    "position": null,
    "team": null,
    "identifiers": {
      "sleeper_id": null,
      "espn_id": "7459",
      "gsis_id": null
    },
    "height": null,
    "weight": null,
    "college": null,
    "age": null,
    "years_exp": null,
    "birth_date": null
  },
  "nfl": {
    "bio": {
      "gsis_id": "00-0007686",
      "display_name": "Thomas Homco",
      "common_first_name": "Thomas",
      "first_name": "Thomas",
      "last_name": "Homco",
      "short_name": null,
      "football_name": null,
      "suffix": null,
      "esb_id": "HOM575019",
      "nfl_id": null,
      "pfr_id": "HomcTh20",
      "pff_id": null,
      "otc_id": null,
      "espn_id": "7459",
      "smart_id": "3200484f-4d57-5019-3ea2-4950c759aab8",
      "birth_date": "1970-01-08",
      "position_group": "LB",
      "position": "LB",
      "ngs_position_group": null,
      "ngs_position": null,
      "height": 72.0,
      "weight": 245.0,
      "headshot": "https://static.www.nfl.com/image/private/f_auto,q_auto/league/isvx2ploprdfmrqapqjn",
      "college_name": "Northwestern",
      "college_conference": null,
      "jersey_number": "57",
      "rookie_season": 1993,
      "last_season": 1996,
      "latest_team": "LA",
      "status": "RES",
      "ngs_status": null,
      "ngs_status_short_description": null,
      "years_of_experience": 4,
      "pff_position": null,
      "pff_status": null,
      "draft_year": null,
      "draft_round": null,
      "draft_pick": null,
      "draft_team": null
    },
    "stats": [],
    "sportradar": {}
  }
}