{
  "id": "espn:2166",
  "fantasy": {
    "id": "espn:2166",
    "name": "John Engelberger",
    "position": null,
    "team": null,
    "identifiers": {
      "sleeper_id": null,
      "espn_id": "2166",
      "gsis_id": null
    },
    "height": null,
    "weight": null,
    "college": null,
    "age": null,
    "years_exp": null,
    "birth_date": null
  },
  "nfl": {
    "bio": {
      "gsis_id": "00-0019651",
      "display_name": "John Engelberger",
      "common_first_name": "John",
      "first_name": "John",
      "last_name": "Engelberger",
      "short_name": null,
      "football_name": null,
      "suffix": null,
      "esb_id": "ENG186880",
      "nfl_id": "25344",
      "pfr_id": "EngeJo20",
      "pff_id": "608",
      "otc_id": null,
      "espn_id": "2166",
      "smart_id": "3200454e-4718-6880-784f-42b870de57d4",
      "birth_date": "1976-10-18",
      "position_group": "DL",
      "position": "DE",
      "ngs_position_group": null,
      "ngs_position": null,
      "height": 76.0,
      "weight": 260.0,
      "headshot": "https://static.www.nfl.com/image/private/f_auto,q_auto/league/bok5kwubuknsnoop1ugm",
      "college_name": "Virginia Tech",
      "college_conference": null,
      "jersey_number": "60",
      "rookie_season": 2000,
      "last_season": 2008,
      "latest_team": "DEN",
      "status": "ACT",
      "ngs_status": null,
      "ngs_status_short_description": null,
      "years_of_experience": 9,
      "pff_position": null,
      "pff_status": null,
      "draft_year": 2000.0,
      "draft_round": 2.0,
      "draft_pick": 35.0,
      "draft_team": "SF"
    },
    "stats": [],
    "sportradar": {}
  }
}