{
  "id": "espn:15526",
  "fantasy": {
    "id": "espn:15526",
    "name": "Nicolas Jean-Baptiste",
    "position": null,
    "team": null,
    "identifiers": {
      "sleeper_id": null,
      "espn_id": "15526",
      "gsis_id": null
    },
    "height": null,
    "weight": null,
    "college": null,
    "age": null,
    "years_exp": null,
    "birth_date": null
  },
  "nfl": {
    "bio": {
      "gsis_id": "00-0029377",
      "display_name": "Nicolas Jean-Baptiste",
      "common_first_name": "Nicolas",
      "first_name": "Nicolas",
      "last_name": "Jean-Baptiste",
      "short_name": null,
      "football_name": null,
      "suffix": null,
      "esb_id": "JEA411916",
      "nfl_id": null,
      "pfr_id": null,
      "pff_id": null,
      "otc_id": null,
      "espn_id": "15526",
      "smart_id": "32004a45-4141-1916-62dd-61636ce05222",
      "birth_date": "1989-03-08",
      "position_group": "DL",
      "position": "NT",
      "ngs_position_group": null,
      "ngs_position": null,
      "height": 73.0,
      "weight": 337.0,
      "headshot": "https://static.www.nfl.com/image/private/f_auto,q_auto/league/ekubftgey0ojsabck39m",
      "college_name": "Baylor",
      "college_conference": null,
      "jersey_number": "0",
      "rookie_season": 2012,
      "last_season": 2012,
      "latest_team": "IND",
      "status": "CUT",
      "ngs_status": null,
      "ngs_status_short_description": null,
      "years_of_experience": 0,
      "pff_position": null,
      "pff_status": null,
      "draft_year": null,
      "draft_round": null,
      "draft_pick": null,
      "draft_team": null
    },
    "stats": [],
    "sportradar": {}
  }
}