{
  "id": "espn:5481",
  "fantasy": {
    "id": "espn:5481",
    "name": "Derrick Frost",
    "position": null,
    "team": null,
    "identifiers": {
      "sleeper_id": null,
      "espn_id": "5481",
      "gsis_id": null
    },
    "height": null,
    "weight": null,
    "college": null,
    "age": null,
    "years_exp": null,
    "birth_date": null
  },
  "nfl": {
    "bio": {
      "gsis_id": "00-0021500",
      "display_name": "Derrick Frost",
      "common_first_name": "Derrick",
      "first_name": "Derrick",
      "last_name": "Frost",
      "short_name": null,
      "football_name": null,
      "suffix": null,
      "esb_id": "FRO666178",
      "nfl_id": null,
      "pfr_id": "FrosDe20",
      "pff_id": null,
      "otc_id": null,
      "espn_id": "5481",
      "smart_id": "32004652-4f66-6178-e39f-861ce931acaa",
      "birth_date": "1980-11-25",
      "position_group": "SPEC",
      "position": "P",
      "ngs_position_group": null,
      "ngs_position": null,
      "height": 74.0,
      "weight": 210.0,
      "headshot": "https://static.www.nfl.com/image/private/f_auto,q_auto/league/it1uqezmlfdcatlq1n1f",
      "college_name": "Northern Iowa",
      "college_conference": null,
      "jersey_number": "6",
      "rookie_season": 2003,
      "last_season": 2008,
      "latest_team": "GB",
      "status": "CUT",
      "ngs_status": null,
      "ngs_status_short_description": null,
      "years_of_experience": 5,
      "pff_position": null,
      "pff_status": null,
      "draft_year": null,
      "draft_round": null,
      "draft_pick": null,
      "draft_team": null
    },
    "stats": [],
    "sportradar": {}
  }
}