{
  "id": "espn:728",
  "fantasy": {
    "id": "espn:728",
    "name": "James McKnight",
    "position": null,
    "team": null,
    "identifiers": {
      "sleeper_id": null,
      "espn_id": "728",
      "gsis_id": null
    },
    "height": null,
    "weight": null,
    "college": null,
    "age": null,
    "years_exp": null,
    "birth_date": null
  },
  "nfl": {
    "bio": {
      "gsis_id": "00-0010974",
      "display_name": "James McKnight",
      "common_first_name": "James",
      "first_name": "James",
      "last_name": "McKnight",
      "short_name": null,
      "football_name": null,
      "suffix": null,
      "esb_id": "MCK723035",
      "nfl_id": null,
      "pfr_id": "McKnJa00",
      "pff_id": null,
      "otc_id": null,
      "espn_id": "728",
      "smart_id": "32004d43-4b72-3035-bd3d-285cb59ee5be",
      "birth_date": "1972-06-17",
      "position_group": "WR",
      "position": "WR",
      "ngs_position_group": null,
      "ngs_position": null,
      "height": 73.0,
      "weight": 198.0,
      "headshot": "https://static.www.nfl.com/image/private/f_auto,q_auto/league/hi55zfivaqqvhhdzormy",
      "college_name": "Liberty",
      "college_conference": null,
      "jersey_number": "80",
      "rookie_season": 1994,
      "last_season": 2003,
      "latest_team": "MIA",
      "status": "ACT",
      "ngs_status": null,
      "ngs_status_short_description": null,
      "years_of_experience": 10,
      "pff_position": null,
      "pff_status": null,
      "draft_year": null,
      "draft_round": null,
      "draft_pick": null,
      "draft_team": null
    },
    "stats": [],
    "sportradar": {}
  }
}