{
  "id": "espn:3043070",
  "fantasy": {
    "id": "espn:3043070",
    "name": "Leon Brown",
    "position": null,
    "team": null,
    "identifiers": {
      "sleeper_id": null,
      "espn_id": "3043070",
      "gsis_id": null
    },
    "height": null,
    "weight": null,
    "college": null,
    "age": null,
    "years_exp": null,
    "birth_date": null
  },
  "nfl": {
    "bio": {
      "gsis_id": "00-0032099",
      "display_name": "Leon Brown",
      "common_first_name": "Leon",
      "first_name": "Leon",
      "last_name": "Brown",
      "short_name": null,
      "football_name": null,
      "suffix": null,
      "esb_id": "BRO545277",
      "nfl_id": null,
      "pfr_id": null,
      "pff_id": null,
      "otc_id": null,
      "espn_id": "3043070",
      "smart_id": "32004252-4f54-5277-d229-cf59fd317e0c",
      "birth_date": "1993-02-24",
      "position_group": "OL",
      "position": "G",
      "ngs_position_group": null,
      "ngs_position": null,
      "height": 78.0,
      "weight": 320.0,
      "headshot": "https://static.www.nfl.com/image/private/f_auto,q_auto/league/nvgetvmnynjsy5wkijwp",
      "college_name": "Alabama",
      "college_conference": null,
      "jersey_number": "0",
      "rookie_season": 2015,
      "last_season": 2015,
      "latest_team": "BAL",
      "status": "DEV",
      "ngs_status": null,
      "ngs_status_short_description": null,
      "years_of_experience": 0,
      "pff_position": null,
      "pff_status": null,
      "draft_year": null,
      "draft_round": null,
      "draft_pick": null,
      "draft_team": null
    },
    "stats": [],
    "sportradar": {}
  }
}