{
  "id": "espn:2168",
  "fantasy": {
    "id": "espn:2168",
    "name": "Travis Claridge",
    "position": null,
    "team": null,
    "identifiers": {
      "sleeper_id": null,
      "espn_id": "3998293",
      "gsis_id": null
    },
    "height": null,
    "weight": null,
    "college": null,
    "age": null,
    "years_exp": null,
    "birth_date": null
  },
  "nfl": {
    "bio": {
      "gsis_id": "00-0018955",
      "display_name": "Travis Claridge",
      "common_first_name": "Travis",
      "first_name": "Travis",
      "last_name": "Claridge",
      "short_name": null,
      "football_name": null,
      "suffix": null,
      "esb_id": "CLA130369",
      "nfl_id": "25346",
      "pfr_id": "ClarTr20",
      "pff_id": null,
      "otc_id": null,
      "espn_id": "3998293",
      "smart_id": "3200434c-4113-0369-7aae-0f7a9977f568",
      "birth_date": "1978-03-23",
      "position_group": "OL",
      "position": "G",
      "ngs_position_group": null,
      "ngs_position": null,
      "height": 77.0,
      "weight": 300.0,
      "headshot": "https://static.www.nfl.com/image/private/f_auto,q_auto/league/nvjgflyzqhidvcptdkdg",
      "college_name": "USC",
      "college_conference": null,
      "jersey_number": "71",
      "rookie_season": 2000,
      "last_season": 2003,
      "latest_team": "ATL",
      "status": "RES",
      "ngs_status": null,
      "ngs_status_short_description": null,
      "years_of_experience": 4,
      "pff_position": null,
      "pff_status": null,
      "draft_year": 2000.0,
      "draft_round": 2.0,
      "draft_pick": 37.0,
      "draft_team": "ATL"
    },
    "stats": [],
    "sportradar": {}
  }
}