{
  "id": "espn:7794",
  "fantasy": {
    "id": "espn:7794",
    "name": "Dunstan Anderson",
    "position": null,
    "team": null,
    "identifiers": {
      "sleeper_id": null,
      "espn_id": "7794",
      "gsis_id": null
    },
    "height": null,
    "weight": null,
    "college": null,
    "age": null,
    "years_exp": null,
    "birth_date": null
  },
  "nfl": {
    "bio": {
      "gsis_id": "00-0000303",
      "display_name": "Dunstan Anderson",
      "common_first_name": "Dunstan",
      "first_name": "Dunstan",
      "last_name": "Anderson",
      "short_name": null,
      "football_name": null,
      "suffix": null,
      "esb_id": "AND200047",
      "nfl_id": null,
      "pfr_id": "AndeDu20",
      "pff_id": null,
      "otc_id": null,
      "espn_id": "7794",
      "smart_id": "3200414e-4420-0047-31cb-cd46638a142f",
      "birth_date": "1970-12-31",
      "position_group": "DL",
      "position": "DE",
      "ngs_position_group": null,
      "ngs_position": null,
      "height": 75.0,
      "weight": 265.0,
      "headshot": "https://static.www.nfl.com/image/private/f_auto,q_auto/league/odfvyqqsjjqwwkkmb4bu",
      "college_name": "Tulsa",
      "college_conference": null,
      "jersey_number": "71",
      "rookie_season": 1994,
      "last_season": 1997,
      "latest_team": "MIA",
      "status": "CUT",
      "ngs_status": null,
      "ngs_status_short_description": null,
      "years_of_experience": 1,
      "pff_position": null,
      "pff_status": null,
      "draft_year": null,
      "draft_round": null,
      "draft_pick": null,
      "draft_team": null
    },
    "stats": [],
    "sportradar": {}
  }
}