{
  "id": "espn:14155",
  "fantasy": {
    "id": "espn:14155",
    "name": "Brandyn Thompson",
    "position": null,
    "team": null,
    "identifiers": {
      "sleeper_id": null,
      "espn_id": "14155",
      "gsis_id": null
    },
    "height": null,
    "weight": null,
    "college": null,
    "age": null,
    "years_exp": null,
    "birth_date": null
  },
  "nfl": {
    "bio": {
      "gsis_id": "00-0028151",
      "display_name": "Brandyn Thompson",
      "common_first_name": "Brandyn",
      "first_name": "Brandyn",
      "last_name": "Thompson",
      "short_name": null,
      "football_name": null,
      "suffix": null,
      "esb_id": "THO494053",
      "nfl_id": "37288",
      "pfr_id": "ThomBr00",
      "pff_id": "6365",
      "otc_id": "6727",
      "espn_id": "14155",
      "smart_id": "32005448-4f49-4053-d0e0-03014b4e831c",
      "birth_date": "1989-10-30",
      "position_group": "DB",
      "position": "DB",
      "ngs_position_group": null,
      "ngs_position": null,
      "height": 70.0,
      "weight": 188.0,
      "headshot": "https://static.www.nfl.com/image/private/f_auto,q_auto/league/yjz6irohuoe5xtavuu78",
      "college_name": "Boise State",
      "college_conference": null,
      "jersey_number": "32",
      "rookie_season": 2011,
      "last_season": 2011,
      "latest_team": "WAS",
      "status": "ACT",
      "ngs_status": null,
      "ngs_status_short_description": null,
      "years_of_experience": 0,
      "pff_position": "CB",
      "pff_status": null,
      "draft_year": 2011.0,
      "draft_round": 7.0,
      "draft_pick": 213.0,
      "draft_team": "WAS"
    },
    "stats": [],
    "sportradar": {}
  }
}