{
  "id": "espn:16510",
  "fantasy": {
    "id": "espn:16510",
    "name": "Akeem Auguste",
    "position": null,
    "team": null,
    "identifiers": {
      "sleeper_id": null,
      "espn_id": "16510",
      "gsis_id": null
    },
    "height": null,
    "weight": null,
    "college": null,
    "age": null,
    "years_exp": null,
    "birth_date": null
  },
  "nfl": {
    "bio": {
      "gsis_id": "00-0030359",
      "display_name": "Akeem Auguste",
      "common_first_name": "Akeem",
      "first_name": "Akeem",
      "last_name": "Auguste",
      "short_name": null,
      "football_name": null,
      "suffix": null,
      "esb_id": "AUG542470",
      "nfl_id": null,
      "pfr_id": "AuguAk00",
      "pff_id": "8405",
      "otc_id": "2849",
      "espn_id": "16510",
      "smart_id": "32004155-4754-2470-4669-13eab92217c7",
      "birth_date": "1989-10-10",
      "position_group": "DB",
      "position": "DB",
      "ngs_position_group": null,
      "ngs_position": null,
      "height": 70.0,
      "weight": 185.0,
      "headshot": "https://static.www.nfl.com/image/private/f_auto,q_auto/league/cpaltrpyrnywlirz2hjz",
      "college_name": "South Carolina",
      "college_conference": null,
      "jersey_number": "0",
      "rookie_season": 2013,
      "last_season": 2013,
      "latest_team": "SEA",
      "status": "DEV",
      "ngs_status": null,
      "ngs_status_short_description": null,
      "years_of_experience": 0,
      "pff_position": null,
      "pff_status": null,
      "draft_year": null,
      "draft_round": null,
      "draft_pick": null,
      "draft_team": null
    },
    "stats": [],
    "sportradar": {}
  }
}