{
  "id": "espn:4259979",
  "fantasy": {
    "id": "espn:4259979",
    "name": "Lynn Bowden Jr.",
    "position": null,
    "team": null,
    "identifiers": {
      "sleeper_id": null,
      "espn_id": "4259979",
      "gsis_id": null
    },
    "height": null,
    "weight": null,
    "college": null,
    "age": null,
    "years_exp": null,
    "birth_date": null
  },
  "nfl": {
    "bio": {
      "gsis_id": "00-0036364",
      "display_name": "Lynn Bowden",
      "common_first_name": "Lynn",
      "first_name": "Lynn",
      "last_name": "Bowden",
      "short_name": "L.Bowden",
      "football_name": "Lynn",
      "suffix": null,
      "esb_id": "BOW068668",
      "nfl_id": "52488",
      "pfr_id": "BowdLy00",
      "pff_id": "61361",
      "otc_id": "8820",
      "espn_id": "4259979",
      "smart_id": "3200424f-5706-8668-b439-a993ac0e9d5d",
      "birth_date": "1997-10-14",
      "position_group": "WR",
      "position": "WR",
      "ngs_position_group": "WR",
      "ngs_position": "WR",
      "height": 73.0,
      "weight": 204.0,
      "headshot": "https://static.www.nfl.com/image/private/f_auto,q_auto/league/nrvwudvuqxpmiegmjzdu",
      "college_name": "Kentucky",
      "college_conference": "Southeastern Conference",
      "jersey_number": "84",
      "rookie_season": 2020,
      "last_season": 2023,
      "latest_team": "NO",
      "status": "ACT",
      "ngs_status": "ACT",
      "ngs_status_short_description": "Active",
      "years_of_experience": 3,
      "pff_position": "WR",
      "pff_status": "A",
      "draft_year": 2020.0,
      "draft_round": 3.0,
      "draft_pick": 80.0,
      "draft_team": "LV"
    },
    "stats": [
      {
        "player_id": "00-0036364",
        "player_name": "L.Bowden",
        "player_display_name": "Lynn Bowden",
        "position": "WR",
        "position_group": "WR",
        "headshot_url": "https://static.www.nfl.com/image/private/f_auto,q_auto/league/nrvwudvuqxpmiegmjzdu",
        "season": 2020,
        "week": 2,
        "season_type": "REG",
        "team": "MIA",
        "opponent_team": "BUF",
        "completions": 0,
        "attempts": 0,
        "passing_yards": 0,
        "passing_tds": 0,
        "passing_interceptions": 0,
        "sacks_suffered": 0,
        "sack_yards_lost": 0,
        "sack_fumbles": 0,
        "sack_fumbles_lost": 0,
        "passing_air_yards": 0,
        "passing_yards_after_catch": 0,
        "passing_first_downs": 0,
        "passing_epa": NaN,
        "passing_cpoe": NaN,
        "passing_2pt_conversions": 0,
        "pacr": NaN,
        "carries": 0,
        "rushing_yards": 0,
        "rushing_tds": 0,
        "rushing_fumbles": 0,
        "rushing_fumbles_lost": 0,
        "rushing_first_downs": 0,
        "rushing_epa": NaN,
        "rushing_2pt_conversions": 0,
        "receptions": 1,
        "targets": 1,
        "receiving_yards": -1,
        "receiving_tds": 0,
        "receiving_fumbles": 0,
        "receiving_fumbles_lost": 0,
        "receiving_air_yards": -1,
        "receiving_yards_after_catch": 0,
        "receiving_first_downs": 0,
        "receiving_epa": -0.7106250962242484,
        "receiving_2pt_conversions": 0,
        "racr": 0.0,
        "target_share": 0.021739130434782608,
        "air_yards_share": -0.003194888178913738,
        "wopr": 0.030372273926934295,
        "special_teams_tds": 0,
        "def_tackles_solo": 0,
        "def_tackles_with_assist": 0,
        "def_tackle_assists": 0,
        "def_tackles_for_loss": 0,
        "def_tackles_for_loss_yards": 0,
        "def_fumbles_forced": 0,
        "def_sacks": 0.0,
        "def_sack_yards": 0.0,
        "def_qb_hits": 0,
        "def_interceptions": 0,
        "def_interception_yards": 0,
        "def_pass_defended": 0,
        "def_tds": 0,
        "def_fumbles": 0,
        "def_safeties": 0,
        "misc_yards": 0,
        "fumble_recovery_own": 0,
        "fumble_recovery_yards_own": 0,
        "fumble_recovery_opp": 0,
        "fumble_recovery_yards_opp": 0,
        "fumble_recovery_tds": 0,
        "penalties": 0,
        "penalty_yards": 0,
        "punt_returns": 0,
        "punt_return_yards": 0,
        "kickoff_returns": 0,
        "kickoff_return_yards": 0,
        "fg_made": 0,
        "fg_att": 0,
        "fg_missed": 0,
        "fg_blocked": 0,
        "fg_long": NaN,
        "fg_pct": NaN,
        "fg_made_0_19": 0,
        "fg_made_20_29": 0,
        "fg_made_30_39": 0,
        "fg_made_40_49": 0,
        "fg_made_50_59": 0,
        "fg_made_60_": 0,
        "fg_missed_0_19": 0,
        "fg_missed_20_29": 0,
        "fg_missed_30_39": 0,
        "fg_missed_40_49": 0,
        "fg_missed_50_59": 0,
        "fg_missed_60_": 0,
        "fg_made_list": null,
        "fg_missed_list": null,
        "fg_blocked_list": null,
        "fg_made_distance": 0,
        "fg_missed_distance": 0,
        "fg_blocked_distance": 0,
        "pat_made": 0,
        "pat_att": 0,
        "pat_missed": 0,
        "pat_blocked": 0,
        "pat_pct": NaN,
        "gwfg_made": 0,
        "gwfg_att": 0,
        "gwfg_missed": 0,
        "gwfg_blocked": 0,
        "gwfg_distance": 0,
        "fantasy_points": -0.1,
        "fantasy_points_ppr": 0.9
      },
      {
        "player_id": "00-0036364",
        "player_name": "L.Bowden",
        "player_display_name": "Lynn Bowden",
        "position": "WR",
        "position_group": "WR",
        "headshot_url": "https://static.www.nfl.com/image/private/f_auto,q_auto/league/nrvwudvuqxpmiegmjzdu",
        "season": 2020,
        "week": 4,
        "season_type": "REG",
        "team": "MIA",
        "opponent_team": "SEA",
        "completions": 0,
        "attempts": 0,
        "passing_yards": 0,
        "passing_tds": 0,
        "passing_interceptions": 0,
        "sacks_suffered": 0,
        "sack_yards_lost": 0,
        "sack_fumbles": 0,
        "sack_fumbles_lost": 0,
        "passing_air_yards": 0,
        "passing_yards_after_catch": 0,
        "passing_first_downs": 0,
        "passing_epa": NaN,
        "passing_cpoe": NaN,
        "passing_2pt_conversions": 0,
        "pacr": NaN,
        "carries": 1,
        "rushing_yards": 5,
        "rushing_tds": 0,
        "rushing_fumbles": 0,
        "rushing_fumbles_lost": 0,
        "rushing_first_downs": 0,
        "rushing_epa": 0.04724109260132536,
        "rushing_2pt_conversions": 0,
        "receptions": 0,
        "targets": 0,
        "receiving_yards": 0,
        "receiving_tds": 0,
        "receiving_fumbles": 0,
        "receiving_fumbles_lost": 0,
        "receiving_air_yards": 0,
        "receiving_yards_after_catch": 0,
        "receiving_first_downs": 0,
        "receiving_epa": NaN,
        "receiving_2pt_conversions": 0,
        "racr": NaN,
        "target_share": 0.0,
        "air_yards_share": 0.0,
        "wopr": 0.0,
        "special_teams_tds": 0,
        "def_tackles_solo": 0,
        "def_tackles_with_assist": 0,
        "def_tackle_assists": 0,
        "def_tackles_for_loss": 0,
        "def_tackles_for_loss_yards": 0,
        "def_fumbles_forced": 0,
        "def_sacks": 0.0,
        "def_sack_yards": 0.0,
        "def_qb_hits": 0,
        "def_interceptions": 0,
        "def_interception_yards": 0,
        "def_pass_defended": 0,
        "def_tds": 0,
        "def_fumbles": 0,
        "def_safeties": 0,
        "misc_yards": 0,
        "fumble_recovery_own": 0,
        "fumble_recovery_yards_own": 0,
        "fumble_recovery_opp": 0,
        "fumble_recovery_yards_opp": 0,
        "fumble_recovery_tds": 0,
        "penalties": 0,
        "penalty_yards": 0,
        "punt_returns": 0,
        "punt_return_yards": 0,
        "kickoff_returns": 0,
        "kickoff_return_yards": 0,
        "fg_made": 0,
        "fg_att": 0,
        "fg_missed": 0,
        "fg_blocked": 0,
        "fg_long": NaN,
        "fg_pct": NaN,
        "fg_made_0_19": 0,
        "fg_made_20_29": 0,
        "fg_made_30_39": 0,
        "fg_made_40_49": 0,
        "fg_made_50_59": 0,
        "fg_made_60_": 0,
        "fg_missed_0_19": 0,
        "fg_missed_20_29": 0,
        "fg_missed_30_39": 0,
        "fg_missed_40_49": 0,
        "fg_missed_50_59": 0,
        "fg_missed_60_": 0,
        "fg_made_list": null,
        "fg_missed_list": null,
        "fg_blocked_list": null,
        "fg_made_distance": 0,
        "fg_missed_distance": 0,
        "fg_blocked_distance": 0,
        "pat_made": 0,
        "pat_att": 0,
        "pat_missed": 0,
        "pat_blocked": 0,
        "pat_pct": NaN,
        "gwfg_made": 0,
        "gwfg_att": 0,
        "gwfg_missed": 0,
        "gwfg_blocked": 0,
        "gwfg_distance": 0,
        "fantasy_points": 0.5,
        "fantasy_points_ppr": 0.5
      },
      {
        "player_id": "00-0036364",
        "player_name": "L.Bowden",
        "player_display_name": "Lynn Bowden",
        "position": "WR",
        "position_group": "WR",
        "headshot_url": "https://static.www.nfl.com/image/private/f_auto,q_auto/league/nrvwudvuqxpmiegmjzdu",
        "season": 2020,
        "week": 5,
        "season_type": "REG",
        "team": "MIA",
        "opponent_team": "SF",
        "completions": 0,
        "attempts": 0,
        "passing_yards": 0,
        "passing_tds": 0,
        "passing_interceptions": 0,
        "sacks_suffered": 0,
        "sack_yards_lost": 0,
        "sack_fumbles": 0,
        "sack_fumbles_lost": 0,
        "passing_air_yards": 0,
        "passing_yards_after_catch": 0,
        "passing_first_downs": 0,
        "passing_epa": NaN,
        "passing_cpoe": NaN,
        "passing_2pt_conversions": 0,
        "pacr": NaN,
        "carries": 3,
        "rushing_yards": 4,
        "rushing_tds": 0,
        "rushing_fumbles": 0,
        "rushing_fumbles_lost": 0,
        "rushing_first_downs": 1,
        "rushing_epa": -0.008550847007427365,
        "rushing_2pt_conversions": 0,
        "receptions": 0,
        "targets": 0,
        "receiving_yards": 0,
        "receiving_tds": 0,
        "receiving_fumbles": 0,
        "receiving_fumbles_lost": 0,
        "receiving_air_yards": 0,
        "receiving_yards_after_catch": 0,
        "receiving_first_downs": 0,
        "receiving_epa": NaN,
        "receiving_2pt_conversions": 0,
        "racr": NaN,
        "target_share": 0.0,
        "air_yards_share": 0.0,
        "wopr": 0.0,
        "special_teams_tds": 0,
        "def_tackles_solo": 0,
        "def_tackles_with_assist": 0,
        "def_tackle_assists": 0,
        "def_tackles_for_loss": 0,
        "def_tackles_for_loss_yards": 0,
        "def_fumbles_forced": 0,
        "def_sacks": 0.0,
        "def_sack_yards": 0.0,
        "def_qb_hits": 0,
        "def_interceptions": 0,
        "def_interception_yards": 0,
        "def_pass_defended": 0,
        "def_tds": 0,
        "def_fumbles": 0,
        "def_safeties": 0,
        "misc_yards": 0,
        "fumble_recovery_own": 0,
        "fumble_recovery_yards_own": 0,
        "fumble_recovery_opp": 0,
        "fumble_recovery_yards_opp": 0,
        "fumble_recovery_tds": 0,
        "penalties": 0,
        "penalty_yards": 0,
        "punt_returns": 0,
        "punt_return_yards": 0,
        "kickoff_returns": 0,
        "kickoff_return_yards": 0,
        "fg_made": 0,
        "fg_att": 0,
        "fg_missed": 0,
        "fg_blocked": 0,
        "fg_long": NaN,
        "fg_pct": NaN,
        "fg_made_0_19": 0,
        "fg_made_20_29": 0,
        "fg_made_30_39": 0,
        "fg_made_40_49": 0,
        "fg_made_50_59": 0,
        "fg_made_60_": 0,
        "fg_missed_0_19": 0,
        "fg_missed_20_29": 0,
        "fg_missed_30_39": 0,
        "fg_missed_40_49": 0,
        "fg_missed_50_59": 0,
        "fg_missed_60_": 0,
        "fg_made_list": null,
        "fg_missed_list": null,
        "fg_blocked_list": null,
        "fg_made_distance": 0,
        "fg_missed_distance": 0,
        "fg_blocked_distance": 0,
        "pat_made": 0,
        "pat_att": 0,
        "pat_missed": 0,
        "pat_blocked": 0,
        "pat_pct": NaN,
        "gwfg_made": 0,
        "gwfg_att": 0,
        "gwfg_missed": 0,
        "gwfg_blocked": 0,
        "gwfg_distance": 0,
        "fantasy_points": 0.4,
        "fantasy_points_ppr": 0.4
      },
      {
        "player_id": "00-0036364",
        "player_name": "L.Bowden",
        "player_display_name": "Lynn Bowden",
        "position": "WR",
        "position_group": "WR",
        "headshot_url": "https://static.www.nfl.com/image/private/f_auto,q_auto/league/nrvwudvuqxpmiegmjzdu",
        "season": 2020,
        "week": 12,
        "season_type": "REG",
        "team": "MIA",
        "opponent_team": "NYJ",
        "completions": 0,
        "attempts": 0,
        "passing_yards": 0,
        "passing_tds": 0,
        "passing_interceptions": 0,
        "sacks_suffered": 0,
        "sack_yards_lost": 0,
        "sack_fumbles": 0,
        "sack_fumbles_lost": 0,
        "passing_air_yards": 0,
        "passing_yards_after_catch": 0,
        "passing_first_downs": 0,
        "passing_epa": NaN,
        "passing_cpoe": NaN,
        "passing_2pt_conversions": 0,
        "pacr": NaN,
        "carries": 0,
        "rushing_yards": 0,
        "rushing_tds": 0,
        "rushing_fumbles": 0,
        "rushing_fumbles_lost": 0,
        "rushing_first_downs": 0,
        "rushing_epa": NaN,
        "rushing_2pt_conversions": 0,
        "receptions": 0,
        "targets": 1,
        "receiving_yards": 0,
        "receiving_tds": 0,
        "receiving_fumbles": 0,
        "receiving_fumbles_lost": 0,
        "receiving_air_yards": 11,
        "receiving_yards_after_catch": 0,
        "receiving_first_downs": 0,
        "receiving_epa": -0.7403604452265427,
        "receiving_2pt_conversions": 0,
        "racr": 0.0,
        "target_share": 0.02564102564102564,
        "air_yards_share": 0.04,
        "wopr": 0.06646153846153846,
        "special_teams_tds": 0,
        "def_tackles_solo": 0,
        "def_tackles_with_assist": 0,
        "def_tackle_assists": 0,
        "def_tackles_for_loss": 0,
        "def_tackles_for_loss_yards": 0,
        "def_fumbles_forced": 0,
        "def_sacks": 0.0,
        "def_sack_yards": 0.0,
        "def_qb_hits": 0,
        "def_interceptions": 0,
        "def_interception_yards": 0,
        "def_pass_defended": 0,
        "def_tds": 0,
        "def_fumbles": 0,
        "def_safeties": 0,
        "misc_yards": 0,
        "fumble_recovery_own": 0,
        "fumble_recovery_yards_own": 0,
        "fumble_recovery_opp": 0,
        "fumble_recovery_yards_opp": 0,
        "fumble_recovery_tds": 0,
        "penalties": 0,
        "penalty_yards": 0,
        "punt_returns": 0,
        "punt_return_yards": 0,
        "kickoff_returns": 0,
        "kickoff_return_yards": 0,
        "fg_made": 0,
        "fg_att": 0,
        "fg_missed": 0,
        "fg_blocked": 0,
        "fg_long": NaN,
        "fg_pct": NaN,
        "fg_made_0_19": 0,
        "fg_made_20_29": 0,
        "fg_made_30_39": 0,
        "fg_made_40_49": 0,
        "fg_made_50_59": 0,
        "fg_made_60_": 0,
        "fg_missed_0_19": 0,
        "fg_missed_20_29": 0,
        "fg_missed_30_39": 0,
        "fg_missed_40_49": 0,
        "fg_missed_50_59": 0,
        "fg_missed_60_": 0,
        "fg_made_list": null,
        "fg_missed_list": null,
        "fg_blocked_list": null,
        "fg_made_distance": 0,
        "fg_missed_distance": 0,
        "fg_blocked_distance": 0,
        "pat_made": 0,
        "pat_att": 0,
        "pat_missed": 0,
        "pat_blocked": 0,
        "pat_pct": NaN,
        "gwfg_made": 0,
        "gwfg_att": 0,
        "gwfg_missed": 0,
        "gwfg_blocked": 0,
        "gwfg_distance": 0,
        "fantasy_points": 0.0,
        "fantasy_points_ppr": 0.0
      },
      {
        "player_id": "00-0036364",
        "player_name": "L.Bowden",
        "player_display_name": "Lynn Bowden",
        "position": "WR",
        "position_group": "WR",
        "headshot_url": "https://static.www.nfl.com/image/private/f_auto,q_auto/league/nrvwudvuqxpmiegmjzdu",
        "season": 2020,
        "week": 13,
        "season_type": "REG",
        "team": "MIA",
        "opponent_team": "CIN",
        "completions": 0,
        "attempts": 0,
        "passing_yards": 0,
        "passing_tds": 0,
        "passing_interceptions": 0,
        "sacks_suffered": 0,
        "sack_yards_lost": 0,
        "sack_fumbles": 0,
        "sack_fumbles_lost": 0,
        "passing_air_yards": 0,
        "passing_yards_after_catch": 0,
        "passing_first_downs": 0,
        "passing_epa": NaN,
        "passing_cpoe": NaN,
        "passing_2pt_conversions": 0,
        "pacr": NaN,
        "carries": 1,
        "rushing_yards": 11,
        "rushing_tds": 0,
        "rushing_fumbles": 0,
        "rushing_fumbles_lost": 0,
        "rushing_first_downs": 1,
        "rushing_epa": 1.0924940817058086,
        "rushing_2pt_conversions": 0,
        "receptions": 4,
        "targets": 4,
        "receiving_yards": 41,
        "receiving_tds": 0,
        "receiving_fumbles": 0,
        "receiving_fumbles_lost": 0,
        "receiving_air_yards": 17,
        "receiving_yards_after_catch": 24,
        "receiving_first_downs": 2,
        "receiving_epa": 3.285029158287216,
        "receiving_2pt_conversions": 0,
        "racr": 2.411764705882353,
        "target_share": 0.10526315789473684,
        "air_yards_share": 0.05704697986577181,
        "wopr": 0.19782762274814553,
        "special_teams_tds": 0,
        "def_tackles_solo": 0,
        "def_tackles_with_assist": 0,
        "def_tackle_assists": 0,
        "def_tackles_for_loss": 0,
        "def_tackles_for_loss_yards": 0,
        "def_fumbles_forced": 0,
        "def_sacks": 0.0,
        "def_sack_yards": 0.0,
        "def_qb_hits": 0,
        "def_interceptions": 0,
        "def_interception_yards": 0,
        "def_pass_defended": 0,
        "def_tds": 0,
        "def_fumbles": 0,
        "def_safeties": 0,
        "misc_yards": 0,
        "fumble_recovery_own": 0,
        "fumble_recovery_yards_own": 0,
        "fumble_recovery_opp": 0,
        "fumble_recovery_yards_opp": 0,
        "fumble_recovery_tds": 0,
        "penalties": 0,
        "penalty_yards": 0,
        "punt_returns": 0,
        "punt_return_yards": 0,
        "kickoff_returns": 0,
        "kickoff_return_yards": 0,
        "fg_made": 0,
        "fg_att": 0,
        "fg_missed": 0,
        "fg_blocked": 0,
        "fg_long": NaN,
        "fg_pct": NaN,
        "fg_made_0_19": 0,
        "fg_made_20_29": 0,
        "fg_made_30_39": 0,
        "fg_made_40_49": 0,
        "fg_made_50_59": 0,
        "fg_made_60_": 0,
        "fg_missed_0_19": 0,
        "fg_missed_20_29": 0,
        "fg_missed_30_39": 0,
        "fg_missed_40_49": 0,
        "fg_missed_50_59": 0,
        "fg_missed_60_": 0,
        "fg_made_list": null,
        "fg_missed_list": null,
        "fg_blocked_list": null,
        "fg_made_distance": 0,
        "fg_missed_distance": 0,
        "fg_blocked_distance": 0,
        "pat_made": 0,
        "pat_att": 0,
        "pat_missed": 0,
        "pat_blocked": 0,
        "pat_pct": NaN,
        "gwfg_made": 0,
        "gwfg_att": 0,
        "gwfg_missed": 0,
        "gwfg_blocked": 0,
        "gwfg_distance": 0,
        "fantasy_points": 5.2,
        "fantasy_points_ppr": 9.2
      },
      {
        "player_id": "00-0036364",
        "player_name": "L.Bowden",
        "player_display_name": "Lynn Bowden",
        "position": "WR",
        "position_group": "WR",
        "headshot_url": "https://static.www.nfl.com/image/private/f_auto,q_auto/league/nrvwudvuqxpmiegmjzdu",
        "season": 2020,
        "week": 14,
        "season_type": "REG",
        "team": "MIA",
        "opponent_team": "KC",
        "completions": 0,
        "attempts": 1,
        "passing_yards": 0,
        "passing_tds": 0,
        "passing_interceptions": 0,
        "sacks_suffered": 0,
        "sack_yards_lost": 0,
        "sack_fumbles": 0,
        "sack_fumbles_lost": 0,
        "passing_air_yards": 19,
        "passing_yards_after_catch": 0,
        "passing_first_downs": 0,
        "passing_epa": -0.4953862380934879,
        "passing_cpoe": -39.63533639907837,
        "passing_2pt_conversions": 0,
        "pacr": 0.0,
        "carries": 1,
        "rushing_yards": 2,
        "rushing_tds": 0,
        "rushing_fumbles": 0,
        "rushing_fumbles_lost": 0,
        "rushing_first_downs": 0,
        "rushing_epa": -0.40818404080346227,
        "rushing_2pt_conversions": 0,
        "receptions": 7,
        "targets": 9,
        "receiving_yards": 82,
        "receiving_tds": 0,
        "receiving_fumbles": 0,
        "receiving_fumbles_lost": 0,
        "receiving_air_yards": 84,
        "receiving_yards_after_catch": 26,
        "receiving_first_downs": 6,
        "receiving_epa": 2.8872335309728414,
        "receiving_2pt_conversions": 0,
        "racr": 0.9761904761904762,
        "target_share": 0.1956521739130435,
        "air_yards_share": 0.18025751072961374,
        "wopr": 0.4196585183802949,
        "special_teams_tds": 0,
        "def_tackles_solo": 0,
        "def_tackles_with_assist": 0,
        "def_tackle_assists": 0,
        "def_tackles_for_loss": 0,
        "def_tackles_for_loss_yards": 0,
        "def_fumbles_forced": 0,
        "def_sacks": 0.0,
        "def_sack_yards": 0.0,
        "def_qb_hits": 0,
        "def_interceptions": 0,
        "def_interception_yards": 0,
        "def_pass_defended": 0,
        "def_tds": 0,
        "def_fumbles": 0,
        "def_safeties": 0,
        "misc_yards": 0,
        "fumble_recovery_own": 0,
        "fumble_recovery_yards_own": 0,
        "fumble_recovery_opp": 0,
        "fumble_recovery_yards_opp": 0,
        "fumble_recovery_tds": 0,
        "penalties": 0,
        "penalty_yards": 0,
        "punt_returns": 0,
        "punt_return_yards": 0,
        "kickoff_returns": 0,
        "kickoff_return_yards": 0,
        "fg_made": 0,
        "fg_att": 0,
        "fg_missed": 0,
        "fg_blocked": 0,
        "fg_long": NaN,
        "fg_pct": NaN,
        "fg_made_0_19": 0,
        "fg_made_20_29": 0,
        "fg_made_30_39": 0,
        "fg_made_40_49": 0,
        "fg_made_50_59": 0,
        "fg_made_60_": 0,
        "fg_missed_0_19": 0,
        "fg_missed_20_29": 0,
        "fg_missed_30_39": 0,
        "fg_missed_40_49": 0,
        "fg_missed_50_59": 0,
        "fg_missed_60_": 0,
        "fg_made_list": null,
        "fg_missed_list": null,
        "fg_blocked_list": null,
        "fg_made_distance": 0,
        "fg_missed_distance": 0,
        "fg_blocked_distance": 0,
        "pat_made": 0,
        "pat_att": 0,
        "pat_missed": 0,
        "pat_blocked": 0,
        "pat_pct": NaN,
        "gwfg_made": 0,
        "gwfg_att": 0,
        "gwfg_missed": 0,
        "gwfg_blocked": 0,
        "gwfg_distance": 0,
        "fantasy_points": 8.4,
        "fantasy_points_ppr": 15.4
      },
      {
        "player_id": "00-0036364",
        "player_name": "L.Bowden",
        "player_display_name": "Lynn Bowden",
        "position": "WR",
        "position_group": "WR",
        "headshot_url": "https://static.www.nfl.com/image/private/f_auto,q_auto/league/nrvwudvuqxpmiegmjzdu",
        "season": 2020,
        "week": 15,
        "season_type": "REG",
        "team": "MIA",
        "opponent_team": "NE",
        "completions": 0,
        "attempts": 0,
        "passing_yards": 0,
        "passing_tds": 0,
        "passing_interceptions": 0,
        "sacks_suffered": 0,
        "sack_yards_lost": 0,
        "sack_fumbles": 0,
        "sack_fumbles_lost": 0,
        "passing_air_yards": 0,
        "passing_yards_after_catch": 0,
        "passing_first_downs": 0,
        "passing_epa": NaN,
        "passing_cpoe": NaN,
        "passing_2pt_conversions": 0,
        "pacr": NaN,
        "carries": 1,
        "rushing_yards": 9,
        "rushing_tds": 0,
        "rushing_fumbles": 0,
        "rushing_fumbles_lost": 0,
        "rushing_first_downs": 0,
        "rushing_epa": 0.6161165678640828,
        "rushing_2pt_conversions": 0,
        "receptions": 6,
        "targets": 7,
        "receiving_yards": 37,
        "receiving_tds": 0,
        "receiving_fumbles": 0,
        "receiving_fumbles_lost": 0,
        "receiving_air_yards": 14,
        "receiving_yards_after_catch": 26,
        "receiving_first_downs": 2,
        "receiving_epa": -2.890780871442985,
        "receiving_2pt_conversions": 0,
        "racr": 2.642857142857143,
        "target_share": 0.28,
        "air_yards_share": 0.14285714285714285,
        "wopr": 0.52,
        "special_teams_tds": 0,
        "def_tackles_solo": 1,
        "def_tackles_with_assist": 0,
        "def_tackle_assists": 0,
        "def_tackles_for_loss": 0,
        "def_tackles_for_loss_yards": 0,
        "def_fumbles_forced": 0,
        "def_sacks": 0.0,
        "def_sack_yards": 0.0,
        "def_qb_hits": 0,
        "def_interceptions": 0,
        "def_interception_yards": 0,
        "def_pass_defended": 0,
        "def_tds": 0,
        "def_fumbles": 0,
        "def_safeties": 0,
        "misc_yards": 0,
        "fumble_recovery_own": 0,
        "fumble_recovery_yards_own": 0,
        "fumble_recovery_opp": 0,
        "fumble_recovery_yards_opp": 0,
        "fumble_recovery_tds": 0,
        "penalties": 0,
        "penalty_yards": 0,
        "punt_returns": 0,
        "punt_return_yards": 0,
        "kickoff_returns": 0,
        "kickoff_return_yards": 0,
        "fg_made": 0,
        "fg_att": 0,
        "fg_missed": 0,
        "fg_blocked": 0,
        "fg_long": NaN,
        "fg_pct": NaN,
        "fg_made_0_19": 0,
        "fg_made_20_29": 0,
        "fg_made_30_39": 0,
        "fg_made_40_49": 0,
        "fg_made_50_59": 0,
        "fg_made_60_": 0,
        "fg_missed_0_19": 0,
        "fg_missed_20_29": 0,
        "fg_missed_30_39": 0,
        "fg_missed_40_49": 0,
        "fg_missed_50_59": 0,
        "fg_missed_60_": 0,
        "fg_made_list": null,
        "fg_missed_list": null,
        "fg_blocked_list": null,
        "fg_made_distance": 0,
        "fg_missed_distance": 0,
        "fg_blocked_distance": 0,
        "pat_made": 0,
        "pat_att": 0,
        "pat_missed": 0,
        "pat_blocked": 0,
        "pat_pct": NaN,
        "gwfg_made": 0,
        "gwfg_att": 0,
        "gwfg_missed": 0,
        "gwfg_blocked": 0,
        "gwfg_distance": 0,
        "fantasy_points": 4.6000000000000005,
        "fantasy_points_ppr": 10.600000000000001
      },
      {
        "player_id": "00-0036364",
        "player_name": "L.Bowden",
        "player_display_name": "Lynn Bowden",
        "position": "WR",
        "position_group": "WR",
        "headshot_url": "https://static.www.nfl.com/image/private/f_auto,q_auto/league/nrvwudvuqxpmiegmjzdu",
        "season": 2020,
        "week": 16,
        "season_type": "REG",
        "team": "MIA",
        "opponent_team": "LV",
        "completions": 0,
        "attempts": 0,
        "passing_yards": 0,
        "passing_tds": 0,
        "passing_interceptions": 0,
        "sacks_suffered": 0,
        "sack_yards_lost": 0,
        "sack_fumbles": 0,
        "sack_fumbles_lost": 0,
        "passing_air_yards": 0,
        "passing_yards_after_catch": 0,
        "passing_first_downs": 0,
        "passing_epa": NaN,
        "passing_cpoe": NaN,
        "passing_2pt_conversions": 0,
        "pacr": NaN,
        "carries": 1,
        "rushing_yards": 8,
        "rushing_tds": 0,
        "rushing_fumbles": 0,
        "rushing_fumbles_lost": 0,
        "rushing_first_downs": 1,
        "rushing_epa": 0.9975463268347085,
        "rushing_2pt_conversions": 0,
        "receptions": 2,
        "targets": 3,
        "receiving_yards": 8,
        "receiving_tds": 0,
        "receiving_fumbles": 0,
        "receiving_fumbles_lost": 0,
        "receiving_air_yards": 7,
        "receiving_yards_after_catch": 8,
        "receiving_first_downs": 0,
        "receiving_epa": -1.542951094219461,
        "receiving_2pt_conversions": 0,
        "racr": 1.1428571428571428,
        "target_share": 0.08823529411764706,
        "air_yards_share": 0.030042918454935622,
        "wopr": 0.1533829840949255,
        "special_teams_tds": 0,
        "def_tackles_solo": 0,
        "def_tackles_with_assist": 0,
        "def_tackle_assists": 0,
        "def_tackles_for_loss": 0,
        "def_tackles_for_loss_yards": 0,
        "def_fumbles_forced": 0,
        "def_sacks": 0.0,
        "def_sack_yards": 0.0,
        "def_qb_hits": 0,
        "def_interceptions": 0,
        "def_interception_yards": 0,
        "def_pass_defended": 0,
        "def_tds": 0,
        "def_fumbles": 0,
        "def_safeties": 0,
        "misc_yards": 0,
        "fumble_recovery_own": 0,
        "fumble_recovery_yards_own": 0,
        "fumble_recovery_opp": 0,
        "fumble_recovery_yards_opp": 0,
        "fumble_recovery_tds": 0,
        "penalties": 0,
        "penalty_yards": 0,
        "punt_returns": 0,
        "punt_return_yards": 0,
        "kickoff_returns": 0,
        "kickoff_return_yards": 0,
        "fg_made": 0,
        "fg_att": 0,
        "fg_missed": 0,
        "fg_blocked": 0,
        "fg_long": NaN,
        "fg_pct": NaN,
        "fg_made_0_19": 0,
        "fg_made_20_29": 0,
        "fg_made_30_39": 0,
        "fg_made_40_49": 0,
        "fg_made_50_59": 0,
        "fg_made_60_": 0,
        "fg_missed_0_19": 0,
        "fg_missed_20_29": 0,
        "fg_missed_30_39": 0,
        "fg_missed_40_49": 0,
        "fg_missed_50_59": 0,
        "fg_missed_60_": 0,
        "fg_made_list": null,
        "fg_missed_list": null,
        "fg_blocked_list": null,
        "fg_made_distance": 0,
        "fg_missed_distance": 0,
        "fg_blocked_distance": 0,
        "pat_made": 0,
        "pat_att": 0,
        "pat_missed": 0,
        "pat_blocked": 0,
        "pat_pct": NaN,
        "gwfg_made": 0,
        "gwfg_att": 0,
        "gwfg_missed": 0,
        "gwfg_blocked": 0,
        "gwfg_distance": 0,
        "fantasy_points": 1.6,
        "fantasy_points_ppr": 3.6
      },
      {
        "player_id": "00-0036364",
        "player_name": "L.Bowden",
        "player_display_name": "Lynn Bowden",
        "position": "WR",
        "position_group": "WR",
        "headshot_url": "https://static.www.nfl.com/image/private/f_auto,q_auto/league/nrvwudvuqxpmiegmjzdu",
        "season": 2020,
        "week": 17,
        "season_type": "REG",
        "team": "MIA",
        "opponent_team": "BUF",
        "completions": 1,
        "attempts": 1,
        "passing_yards": 32,
        "passing_tds": 0,
        "passing_interceptions": 0,
        "sacks_suffered": 0,
        "sack_yards_lost": 0,
        "sack_fumbles": 0,
        "sack_fumbles_lost": 0,
        "passing_air_yards": -2,
        "passing_yards_after_catch": 34,
        "passing_first_downs": 1,
        "passing_epa": 2.3460596356308088,
        "passing_cpoe": 12.810266017913818,
        "passing_2pt_conversions": 0,
        "pacr": 0.0,
        "carries": 1,
        "rushing_yards": -7,
        "rushing_tds": 0,
        "rushing_fumbles": 0,
        "rushing_fumbles_lost": 0,
        "rushing_first_downs": 0,
        "rushing_epa": -1.7470413957489654,
        "rushing_2pt_conversions": 0,
        "receptions": 8,
        "targets": 12,
        "receiving_yards": 44,
        "receiving_tds": 0,
        "receiving_fumbles": 0,
        "receiving_fumbles_lost": 0,
        "receiving_air_yards": 53,
        "receiving_yards_after_catch": 28,
        "receiving_first_downs": 3,
        "receiving_epa": -7.284535747894552,
        "receiving_2pt_conversions": 0,
        "racr": 0.8301886792452831,
        "target_share": 0.2033898305084746,
        "air_yards_share": 0.12045454545454545,
        "wopr": 0.3894029275808937,
        "special_teams_tds": 0,
        "def_tackles_solo": 1,
        "def_tackles_with_assist": 0,
        "def_tackle_assists": 0,
        "def_tackles_for_loss": 0,
        "def_tackles_for_loss_yards": 0,
        "def_fumbles_forced": 0,
        "def_sacks": 0.0,
        "def_sack_yards": 0.0,
        "def_qb_hits": 0,
        "def_interceptions": 0,
        "def_interception_yards": 0,
        "def_pass_defended": 0,
        "def_tds": 0,
        "def_fumbles": 0,
        "def_safeties": 0,
        "misc_yards": 0,
        "fumble_recovery_own": 0,
        "fumble_recovery_yards_own": 0,
        "fumble_recovery_opp": 0,
        "fumble_recovery_yards_opp": 0,
        "fumble_recovery_tds": 0,
        "penalties": 0,
        "penalty_yards": 0,
        "punt_returns": 0,
        "punt_return_yards": 0,
        "kickoff_returns": 0,
        "kickoff_return_yards": 0,
        "fg_made": 0,
        "fg_att": 0,
        "fg_missed": 0,
        "fg_blocked": 0,
        "fg_long": NaN,
        "fg_pct": NaN,
        "fg_made_0_19": 0,
        "fg_made_20_29": 0,
        "fg_made_30_39": 0,
        "fg_made_40_49": 0,
        "fg_made_50_59": 0,
        "fg_made_60_": 0,
        "fg_missed_0_19": 0,
        "fg_missed_20_29": 0,
        "fg_missed_30_39": 0,
        "fg_missed_40_49": 0,
        "fg_missed_50_59": 0,
        "fg_missed_60_": 0,
        "fg_made_list": null,
        "fg_missed_list": null,
        "fg_blocked_list": null,
        "fg_made_distance": 0,
        "fg_missed_distance": 0,
        "fg_blocked_distance": 0,
        "pat_made": 0,
        "pat_att": 0,
        "pat_missed": 0,
        "pat_blocked": 0,
        "pat_pct": NaN,
        "gwfg_made": 0,
        "gwfg_att": 0,
        "gwfg_missed": 0,
        "gwfg_blocked": 0,
        "gwfg_distance": 0,
        "fantasy_points": 4.98,
        "fantasy_points_ppr": 12.98
      },
      {
        "player_id": "00-0036364",
        "player_name": "L.Bowden",
        "player_display_name": "Lynn Bowden",
        "position": "WR",
        "position_group": "WR",
        "headshot_url": "https://static.www.nfl.com/image/private/f_auto,q_auto/league/nrvwudvuqxpmiegmjzdu",
        "season": 2023,
        "week": 4,
        "season_type": "REG",
        "team": "NO",
        "opponent_team": "TB",
        "completions": 0,
        "attempts": 0,
        "passing_yards": 0,
        "passing_tds": 0,
        "passing_interceptions": 0,
        "sacks_suffered": 0,
        "sack_yards_lost": 0,
        "sack_fumbles": 0,
        "sack_fumbles_lost": 0,
        "passing_air_yards": 0,
        "passing_yards_after_catch": 0,
        "passing_first_downs": 0,
        "passing_epa": NaN,
        "passing_cpoe": NaN,
        "passing_2pt_conversions": 0,
        "pacr": NaN,
        "carries": 0,
        "rushing_yards": 0,
        "rushing_tds": 0,
        "rushing_fumbles": 0,
        "rushing_fumbles_lost": 0,
        "rushing_first_downs": 0,
        "rushing_epa": NaN,
        "rushing_2pt_conversions": 0,
        "receptions": 0,
        "targets": 1,
        "receiving_yards": 0,
        "receiving_tds": 0,
        "receiving_fumbles": 0,
        "receiving_fumbles_lost": 0,
        "receiving_air_yards": 9,
        "receiving_yards_after_catch": 0,
        "receiving_first_downs": 0,
        "receiving_epa": -0.6539391189580783,
        "receiving_2pt_conversions": 0,
        "racr": 0.0,
        "target_share": 0.02631578947368421,
        "air_yards_share": 0.02786377708978328,
        "wopr": 0.05897832817337461,
        "special_teams_tds": 0,
        "def_tackles_solo": 0,
        "def_tackles_with_assist": 0,
        "def_tackle_assists": 0,
        "def_tackles_for_loss": 0,
        "def_tackles_for_loss_yards": 0,
        "def_fumbles_forced": 0,
        "def_sacks": 0.0,
        "def_sack_yards": 0.0,
        "def_qb_hits": 0,
        "def_interceptions": 0,
        "def_interception_yards": 0,
        "def_pass_defended": 0,
        "def_tds": 0,
        "def_fumbles": 0,
        "def_safeties": 0,
        "misc_yards": 0,
        "fumble_recovery_own": 0,
        "fumble_recovery_yards_own": 0,
        "fumble_recovery_opp": 0,
        "fumble_recovery_yards_opp": 0,
        "fumble_recovery_tds": 0,
        "penalties": 0,
        "penalty_yards": 0,
        "punt_returns": 0,
        "punt_return_yards": 0,
        "kickoff_returns": 0,
        "kickoff_return_yards": 0,
        "fg_made": 0,
        "fg_att": 0,
        "fg_missed": 0,
        "fg_blocked": 0,
        "fg_long": NaN,
        "fg_pct": NaN,
        "fg_made_0_19": 0,
        "fg_made_20_29": 0,
        "fg_made_30_39": 0,
        "fg_made_40_49": 0,
        "fg_made_50_59": 0,
        "fg_made_60_": 0,
        "fg_missed_0_19": 0,
        "fg_missed_20_29": 0,
        "fg_missed_30_39": 0,
        "fg_missed_40_49": 0,
        "fg_missed_50_59": 0,
        "fg_missed_60_": 0,
        "fg_made_list": null,
        "fg_missed_list": null,
        "fg_blocked_list": null,
        "fg_made_distance": 0,
        "fg_missed_distance": 0,
        "fg_blocked_distance": 0,
        "pat_made": 0,
        "pat_att": 0,
        "pat_missed": 0,
        "pat_blocked": 0,
        "pat_pct": NaN,
        "gwfg_made": 0,
        "gwfg_att": 0,
        "gwfg_missed": 0,
        "gwfg_blocked": 0,
        "gwfg_distance": 0,
        "fantasy_points": 0.0,
        "fantasy_points_ppr": 0.0
      },
      {
        "player_id": "00-0036364",
        "player_name": "L.Bowden",
        "player_display_name": "Lynn Bowden",
        "position": "WR",
        "position_group": "WR",
        "headshot_url": "https://static.www.nfl.com/image/private/f_auto,q_auto/league/nrvwudvuqxpmiegmjzdu",
        "season": 2023,
        "week": 10,
        "season_type": "REG",
        "team": "NO",
        "opponent_team": "MIN",
        "completions": 0,
        "attempts": 0,
        "passing_yards": 0,
        "passing_tds": 0,
        "passing_interceptions": 0,
        "sacks_suffered": 0,
        "sack_yards_lost": 0,
        "sack_fumbles": 0,
        "sack_fumbles_lost": 0,
        "passing_air_yards": 0,
        "passing_yards_after_catch": 0,
        "passing_first_downs": 0,
        "passing_epa": NaN,
        "passing_cpoe": NaN,
        "passing_2pt_conversions": 0,
        "pacr": NaN,
        "carries": 0,
        "rushing_yards": 0,
        "rushing_tds": 0,
        "rushing_fumbles": 0,
        "rushing_fumbles_lost": 0,
        "rushing_first_downs": 0,
        "rushing_epa": NaN,
        "rushing_2pt_conversions": 0,
        "receptions": 1,
        "targets": 1,
        "receiving_yards": 12,
        "receiving_tds": 0,
        "receiving_fumbles": 0,
        "receiving_fumbles_lost": 0,
        "receiving_air_yards": 10,
        "receiving_yards_after_catch": 2,
        "receiving_first_downs": 0,
        "receiving_epa": 0.5499926225747913,
        "receiving_2pt_conversions": 0,
        "racr": 1.2,
        "target_share": 0.025,
        "air_yards_share": 0.02066115702479339,
        "wopr": 0.05196280991735538,
        "special_teams_tds": 0,
        "def_tackles_solo": 0,
        "def_tackles_with_assist": 0,
        "def_tackle_assists": 0,
        "def_tackles_for_loss": 0,
        "def_tackles_for_loss_yards": 0,
        "def_fumbles_forced": 0,
        "def_sacks": 0.0,
        "def_sack_yards": 0.0,
        "def_qb_hits": 0,
        "def_interceptions": 0,
        "def_interception_yards": 0,
        "def_pass_defended": 0,
        "def_tds": 0,
        "def_fumbles": 0,
        "def_safeties": 0,
        "misc_yards": 0,
        "fumble_recovery_own": 0,
        "fumble_recovery_yards_own": 0,
        "fumble_recovery_opp": 0,
        "fumble_recovery_yards_opp": 0,
        "fumble_recovery_tds": 0,
        "penalties": 0,
        "penalty_yards": 0,
        "punt_returns": 0,
        "punt_return_yards": 0,
        "kickoff_returns": 0,
        "kickoff_return_yards": 0,
        "fg_made": 0,
        "fg_att": 0,
        "fg_missed": 0,
        "fg_blocked": 0,
        "fg_long": NaN,
        "fg_pct": NaN,
        "fg_made_0_19": 0,
        "fg_made_20_29": 0,
        "fg_made_30_39": 0,
        "fg_made_40_49": 0,
        "fg_made_50_59": 0,
        "fg_made_60_": 0,
        "fg_missed_0_19": 0,
        "fg_missed_20_29": 0,
        "fg_missed_30_39": 0,
        "fg_missed_40_49": 0,
        "fg_missed_50_59": 0,
        "fg_missed_60_": 0,
        "fg_made_list": null,
        "fg_missed_list": null,
        "fg_blocked_list": null,
        "fg_made_distance": 0,
        "fg_missed_distance": 0,
        "fg_blocked_distance": 0,
        "pat_made": 0,
        "pat_att": 0,
        "pat_missed": 0,
        "pat_blocked": 0,
        "pat_pct": NaN,
        "gwfg_made": 0,
        "gwfg_att": 0,
        "gwfg_missed": 0,
        "gwfg_blocked": 0,
        "gwfg_distance": 0,
        "fantasy_points": 1.2000000000000002,
        "fantasy_points_ppr": 2.2
      },
      {
        "player_id": "00-0036364",
        "player_name": "L.Bowden",
        "player_display_name": "Lynn Bowden",
        "position": "WR",
        "position_group": "WR",
        "headshot_url": "https://static.www.nfl.com/image/private/f_auto,q_auto/league/nrvwudvuqxpmiegmjzdu",
        "season": 2023,
        "week": 12,
        "season_type": "REG",
        "team": "NO",
        "opponent_team": "ATL",
        "completions": 0,
        "attempts": 0,
        "passing_yards": 0,
        "passing_tds": 0,
        "passing_interceptions": 0,
        "sacks_suffered": 0,
        "sack_yards_lost": 0,
        "sack_fumbles": 0,
        "sack_fumbles_lost": 0,
        "passing_air_yards": 0,
        "passing_yards_after_catch": 0,
        "passing_first_downs": 0,
        "passing_epa": NaN,
        "passing_cpoe": NaN,
        "passing_2pt_conversions": 0,
        "pacr": NaN,
        "carries": 2,
        "rushing_yards": 40,
        "rushing_tds": 0,
        "rushing_fumbles": 0,
        "rushing_fumbles_lost": 0,
        "rushing_first_downs": 2,
        "rushing_epa": 2.369254026853014,
        "rushing_2pt_conversions": 0,
        "receptions": 0,
        "targets": 2,
        "receiving_yards": 0,
        "receiving_tds": 0,
        "receiving_fumbles": 0,
        "receiving_fumbles_lost": 0,
        "receiving_air_yards": 25,
        "receiving_yards_after_catch": 0,
        "receiving_first_downs": 0,
        "receiving_epa": -1.334097923214077,
        "receiving_2pt_conversions": 0,
        "racr": 0.0,
        "target_share": 0.05405405405405406,
        "air_yards_share": 0.07598784194528875,
        "wopr": 0.1342725704427832,
        "special_teams_tds": 0,
        "def_tackles_solo": 0,
        "def_tackles_with_assist": 0,
        "def_tackle_assists": 0,
        "def_tackles_for_loss": 0,
        "def_tackles_for_loss_yards": 0,
        "def_fumbles_forced": 0,
        "def_sacks": 0.0,
        "def_sack_yards": 0.0,
        "def_qb_hits": 0,
        "def_interceptions": 0,
        "def_interception_yards": 0,
        "def_pass_defended": 0,
        "def_tds": 0,
        "def_fumbles": 0,
        "def_safeties": 0,
        "misc_yards": 0,
        "fumble_recovery_own": 0,
        "fumble_recovery_yards_own": 0,
        "fumble_recovery_opp": 0,
        "fumble_recovery_yards_opp": 0,
        "fumble_recovery_tds": 0,
        "penalties": 0,
        "penalty_yards": 0,
        "punt_returns": 0,
        "punt_return_yards": 0,
        "kickoff_returns": 0,
        "kickoff_return_yards": 0,
        "fg_made": 0,
        "fg_att": 0,
        "fg_missed": 0,
        "fg_blocked": 0,
        "fg_long": NaN,
        "fg_pct": NaN,
        "fg_made_0_19": 0,
        "fg_made_20_29": 0,
        "fg_made_30_39": 0,
        "fg_made_40_49": 0,
        "fg_made_50_59": 0,
        "fg_made_60_": 0,
        "fg_missed_0_19": 0,
        "fg_missed_20_29": 0,
        "fg_missed_30_39": 0,
        "fg_missed_40_49": 0,
        "fg_missed_50_59": 0,
        "fg_missed_60_": 0,
        "fg_made_list": null,
        "fg_missed_list": null,
        "fg_blocked_list": null,
        "fg_made_distance": 0,
        "fg_missed_distance": 0,
        "fg_blocked_distance": 0,
        "pat_made": 0,
        "pat_att": 0,
        "pat_missed": 0,
        "pat_blocked": 0,
        "pat_pct": NaN,
        "gwfg_made": 0,
        "gwfg_att": 0,
        "gwfg_missed": 0,
        "gwfg_blocked": 0,
        "gwfg_distance": 0,
        "fantasy_points": 4.0,
        "fantasy_points_ppr": 4.0
      },
      {
        "player_id": "00-0036364",
        "player_name": "L.Bowden",
        "player_display_name": "Lynn Bowden",
        "position": "WR",
        "position_group": "WR",
        "headshot_url": "https://static.www.nfl.com/image/private/f_auto,q_auto/league/nrvwudvuqxpmiegmjzdu",
        "season": 2023,
        "week": 13,
        "season_type": "REG",
        "team": "NO",
        "opponent_team": "DET",
        "completions": 0,
        "attempts": 0,
        "passing_yards": 0,
        "passing_tds": 0,
        "passing_interceptions": 0,
        "sacks_suffered": 0,
        "sack_yards_lost": 0,
        "sack_fumbles": 0,
        "sack_fumbles_lost": 0,
        "passing_air_yards": 0,
        "passing_yards_after_catch": 0,
        "passing_first_downs": 0,
        "passing_epa": NaN,
        "passing_cpoe": NaN,
        "passing_2pt_conversions": 0,
        "pacr": NaN,
        "carries": 2,
        "rushing_yards": -6,
        "rushing_tds": 0,
        "rushing_fumbles": 0,
        "rushing_fumbles_lost": 0,
        "rushing_first_downs": 1,
        "rushing_epa": -2.299585096887313,
        "rushing_2pt_conversions": 0,
        "receptions": 1,
        "targets": 1,
        "receiving_yards": 5,
        "receiving_tds": 0,
        "receiving_fumbles": 0,
        "receiving_fumbles_lost": 0,
        "receiving_air_yards": 5,
        "receiving_yards_after_catch": 0,
        "receiving_first_downs": 0,
        "receiving_epa": -0.021457648370414972,
        "receiving_2pt_conversions": 0,
        "racr": 1.0,
        "target_share": 0.034482758620689655,
        "air_yards_share": 0.01968503937007874,
        "wopr": 0.0655036654900896,
        "special_teams_tds": 0,
        "def_tackles_solo": 0,
        "def_tackles_with_assist": 0,
        "def_tackle_assists": 0,
        "def_tackles_for_loss": 0,
        "def_tackles_for_loss_yards": 0,
        "def_fumbles_forced": 0,
        "def_sacks": 0.0,
        "def_sack_yards": 0.0,
        "def_qb_hits": 0,
        "def_interceptions": 0,
        "def_interception_yards": 0,
        "def_pass_defended": 0,
        "def_tds": 0,
        "def_fumbles": 0,
        "def_safeties": 0,
        "misc_yards": 0,
        "fumble_recovery_own": 0,
        "fumble_recovery_yards_own": 0,
        "fumble_recovery_opp": 0,
        "fumble_recovery_yards_opp": 0,
        "fumble_recovery_tds": 0,
        "penalties": 0,
        "penalty_yards": 0,
        "punt_returns": 5,
        "punt_return_yards": 30,
        "kickoff_returns": 1,
        "kickoff_return_yards": 18,
        "fg_made": 0,
        "fg_att": 0,
        "fg_missed": 0,
        "fg_blocked": 0,
        "fg_long": NaN,
        "fg_pct": NaN,
        "fg_made_0_19": 0,
        "fg_made_20_29": 0,
        "fg_made_30_39": 0,
        "fg_made_40_49": 0,
        "fg_made_50_59": 0,
        "fg_made_60_": 0,
        "fg_missed_0_19": 0,
        "fg_missed_20_29": 0,
        "fg_missed_30_39": 0,
        "fg_missed_40_49": 0,
        "fg_missed_50_59": 0,
        "fg_missed_60_": 0,
        "fg_made_list": null,
        "fg_missed_list": null,
        "fg_blocked_list": null,
        "fg_made_distance": 0,
        "fg_missed_distance": 0,
        "fg_blocked_distance": 0,
        "pat_made": 0,
        "pat_att": 0,
        "pat_missed": 0,
        "pat_blocked": 0,
        "pat_pct": NaN,
        "gwfg_made": 0,
        "gwfg_att": 0,
        "gwfg_missed": 0,
        "gwfg_blocked": 0,
        "gwfg_distance": 0,
        "fantasy_points": -0.1,
        "fantasy_points_ppr": 0.9
      },
      {
        "player_id": "00-0036364",
        "player_name": "L.Bowden",
        "player_display_name": "Lynn Bowden",
        "position": "WR",
        "position_group": "WR",
        "headshot_url": "https://static.www.nfl.com/image/private/f_auto,q_auto/league/nrvwudvuqxpmiegmjzdu",
        "season": 2023,
        "week": 14,
        "season_type": "REG",
        "team": "NO",
        "opponent_team": "CAR",
        "completions": 0,
        "attempts": 0,
        "passing_yards": 0,
        "passing_tds": 0,
        "passing_interceptions": 0,
        "sacks_suffered": 0,
        "sack_yards_lost": 0,
        "sack_fumbles": 0,
        "sack_fumbles_lost": 0,
        "passing_air_yards": 0,
        "passing_yards_after_catch": 0,
        "passing_first_downs": 0,
        "passing_epa": NaN,
        "passing_cpoe": NaN,
        "passing_2pt_conversions": 0,
        "pacr": NaN,
        "carries": 0,
        "rushing_yards": 0,
        "rushing_tds": 0,
        "rushing_fumbles": 0,
        "rushing_fumbles_lost": 0,
        "rushing_first_downs": 0,
        "rushing_epa": NaN,
        "rushing_2pt_conversions": 0,
        "receptions": 4,
        "targets": 4,
        "receiving_yards": 24,
        "receiving_tds": 0,
        "receiving_fumbles": 0,
        "receiving_fumbles_lost": 0,
        "receiving_air_yards": 0,
        "receiving_yards_after_catch": 24,
        "receiving_first_downs": 1,
        "receiving_epa": 0.5418637490365654,
        "receiving_2pt_conversions": 0,
        "racr": 0.0,
        "target_share": 0.18181818181818182,
        "air_yards_share": 0.0,
        "wopr": 0.2727272727272727,
        "special_teams_tds": 0,
        "def_tackles_solo": 0,
        "def_tackles_with_assist": 0,
        "def_tackle_assists": 0,
        "def_tackles_for_loss": 0,
        "def_tackles_for_loss_yards": 0,
        "def_fumbles_forced": 0,
        "def_sacks": 0.0,
        "def_sack_yards": 0.0,
        "def_qb_hits": 0,
        "def_interceptions": 0,
        "def_interception_yards": 0,
        "def_pass_defended": 0,
        "def_tds": 0,
        "def_fumbles": 0,
        "def_safeties": 0,
        "misc_yards": 0,
        "fumble_recovery_own": 0,
        "fumble_recovery_yards_own": 0,
        "fumble_recovery_opp": 0,
        "fumble_recovery_yards_opp": 0,
        "fumble_recovery_tds": 0,
        "penalties": 0,
        "penalty_yards": 0,
        "punt_returns": 2,
        "punt_return_yards": 23,
        "kickoff_returns": 1,
        "kickoff_return_yards": 28,
        "fg_made": 0,
        "fg_att": 0,
        "fg_missed": 0,
        "fg_blocked": 0,
        "fg_long": NaN,
        "fg_pct": NaN,
        "fg_made_0_19": 0,
        "fg_made_20_29": 0,
        "fg_made_30_39": 0,
        "fg_made_40_49": 0,
        "fg_made_50_59": 0,
        "fg_made_60_": 0,
        "fg_missed_0_19": 0,
        "fg_missed_20_29": 0,
        "fg_missed_30_39": 0,
        "fg_missed_40_49": 0,
        "fg_missed_50_59": 0,
        "fg_missed_60_": 0,
        "fg_made_list": null,
        "fg_missed_list": null,
        "fg_blocked_list": null,
        "fg_made_distance": 0,
        "fg_missed_distance": 0,
        "fg_blocked_distance": 0,
        "pat_made": 0,
        "pat_att": 0,
        "pat_missed": 0,
        "pat_blocked": 0,
        "pat_pct": NaN,
        "gwfg_made": 0,
        "gwfg_att": 0,
        "gwfg_missed": 0,
        "gwfg_blocked": 0,
        "gwfg_distance": 0,
        "fantasy_points": 2.4000000000000004,
        "fantasy_points_ppr": 6.4
      },
      {
        "player_id": "00-0036364",
        "player_name": "L.Bowden",
        "player_display_name": "Lynn Bowden",
        "position": "WR",
        "position_group": "WR",
        "headshot_url": "https://static.www.nfl.com/image/private/f_auto,q_auto/league/nrvwudvuqxpmiegmjzdu",
        "season": 2023,
        "week": 15,
        "season_type": "REG",
        "team": "NO",
        "opponent_team": "NYG",
        "completions": 0,
        "attempts": 0,
        "passing_yards": 0,
        "passing_tds": 0,
        "passing_interceptions": 0,
        "sacks_suffered": 0,
        "sack_yards_lost": 0,
        "sack_fumbles": 0,
        "sack_fumbles_lost": 0,
        "passing_air_yards": 0,
        "passing_yards_after_catch": 0,
        "passing_first_downs": 0,
        "passing_epa": NaN,
        "passing_cpoe": NaN,
        "passing_2pt_conversions": 0,
        "pacr": NaN,
        "carries": 0,
        "rushing_yards": 0,
        "rushing_tds": 0,
        "rushing_fumbles": 0,
        "rushing_fumbles_lost": 0,
        "rushing_first_downs": 0,
        "rushing_epa": NaN,
        "rushing_2pt_conversions": 0,
        "receptions": 3,
        "targets": 5,
        "receiving_yards": 31,
        "receiving_tds": 0,
        "receiving_fumbles": 0,
        "receiving_fumbles_lost": 0,
        "receiving_air_yards": 36,
        "receiving_yards_after_catch": 15,
        "receiving_first_downs": 1,
        "receiving_epa": -0.269477903842926,
        "receiving_2pt_conversions": 0,
        "racr": 0.8611111111111112,
        "target_share": 0.17857142857142858,
        "air_yards_share": 0.1935483870967742,
        "wopr": 0.40334101382488474,
        "special_teams_tds": 0,
        "def_tackles_solo": 0,
        "def_tackles_with_assist": 0,
        "def_tackle_assists": 0,
        "def_tackles_for_loss": 0,
        "def_tackles_for_loss_yards": 0,
        "def_fumbles_forced": 0,
        "def_sacks": 0.0,
        "def_sack_yards": 0.0,
        "def_qb_hits": 0,
        "def_interceptions": 0,
        "def_interception_yards": 0,
        "def_pass_defended": 0,
        "def_tds": 0,
        "def_fumbles": 0,
        "def_safeties": 0,
        "misc_yards": 0,
        "fumble_recovery_own": 0,
        "fumble_recovery_yards_own": 0,
        "fumble_recovery_opp": 0,
        "fumble_recovery_yards_opp": 0,
        "fumble_recovery_tds": 0,
        "penalties": 0,
        "penalty_yards": 0,
        "punt_returns": 0,
        "punt_return_yards": 0,
        "kickoff_returns": 1,
        "kickoff_return_yards": 18,
        "fg_made": 0,
        "fg_att": 0,
        "fg_missed": 0,
        "fg_blocked": 0,
        "fg_long": NaN,
        "fg_pct": NaN,
        "fg_made_0_19": 0,
        "fg_made_20_29": 0,
        "fg_made_30_39": 0,
        "fg_made_40_49": 0,
        "fg_made_50_59": 0,
        "fg_made_60_": 0,
        "fg_missed_0_19": 0,
        "fg_missed_20_29": 0,
        "fg_missed_30_39": 0,
        "fg_missed_40_49": 0,
        "fg_missed_50_59": 0,
        "fg_missed_60_": 0,
        "fg_made_list": null,
        "fg_missed_list": null,
        "fg_blocked_list": null,
        "fg_made_distance": 0,
        "fg_missed_distance": 0,
        "fg_blocked_distance": 0,
        "pat_made": 0,
        "pat_att": 0,
        "pat_missed": 0,
        "pat_blocked": 0,
        "pat_pct": NaN,
        "gwfg_made": 0,
        "gwfg_att": 0,
        "gwfg_missed": 0,
        "gwfg_blocked": 0,
        "gwfg_distance": 0,
        "fantasy_points": 3.1,
        "fantasy_points_ppr": 6.1
      },
      {
        "player_id": "00-0036364",
        "player_name": "L.Bowden",
        "player_display_name": "Lynn Bowden",
        "position": "WR",
        "position_group": "WR",
        "headshot_url": "https://static.www.nfl.com/image/private/f_auto,q_auto/league/nrvwudvuqxpmiegmjzdu",
        "season": 2023,
        "week": 17,
        "season_type": "REG",
        "team": "NO",
        "opponent_team": "TB",
        "completions": 0,
        "attempts": 0,
        "passing_yards": 0,
        "passing_tds": 0,
        "passing_interceptions": 0,
        "sacks_suffered": 0,
        "sack_yards_lost": 0,
        "sack_fumbles": 0,
        "sack_fumbles_lost": 0,
        "passing_air_yards": 0,
        "passing_yards_after_catch": 0,
        "passing_first_downs": 0,
        "passing_epa": NaN,
        "passing_cpoe": NaN,
        "passing_2pt_conversions": 0,
        "pacr": NaN,
        "carries": 0,
        "rushing_yards": 0,
        "rushing_tds": 0,
        "rushing_fumbles": 0,
        "rushing_fumbles_lost": 0,
        "rushing_first_downs": 0,
        "rushing_epa": NaN,
        "rushing_2pt_conversions": 0,
        "receptions": 1,
        "targets": 1,
        "receiving_yards": 6,
        "receiving_tds": 0,
        "receiving_fumbles": 0,
        "receiving_fumbles_lost": 0,
        "receiving_air_yards": -3,
        "receiving_yards_after_catch": 9,
        "receiving_first_downs": 0,
        "receiving_epa": -0.05465741630177945,
        "receiving_2pt_conversions": 0,
        "racr": 0.0,
        "target_share": 0.029411764705882353,
        "air_yards_share": -0.018404907975460124,
        "wopr": 0.031234211476001437,
        "special_teams_tds": 0,
        "def_tackles_solo": 0,
        "def_tackles_with_assist": 0,
        "def_tackle_assists": 0,
        "def_tackles_for_loss": 0,
        "def_tackles_for_loss_yards": 0,
        "def_fumbles_forced": 0,
        "def_sacks": 0.0,
        "def_sack_yards": 0.0,
        "def_qb_hits": 0,
        "def_interceptions": 0,
        "def_interception_yards": 0,
        "def_pass_defended": 0,
        "def_tds": 0,
        "def_fumbles": 0,
        "def_safeties": 0,
        "misc_yards": 0,
        "fumble_recovery_own": 0,
        "fumble_recovery_yards_own": 0,
        "fumble_recovery_opp": 0,
        "fumble_recovery_yards_opp": 0,
        "fumble_recovery_tds": 0,
        "penalties": 0,
        "penalty_yards": 0,
        "punt_returns": 0,
        "punt_return_yards": 0,
        "kickoff_returns": 0,
        "kickoff_return_yards": 0,
        "fg_made": 0,
        "fg_att": 0,
        "fg_missed": 0,
        "fg_blocked": 0,
        "fg_long": NaN,
        "fg_pct": NaN,
        "fg_made_0_19": 0,
        "fg_made_20_29": 0,
        "fg_made_30_39": 0,
        "fg_made_40_49": 0,
        "fg_made_50_59": 0,
        "fg_made_60_": 0,
        "fg_missed_0_19": 0,
        "fg_missed_20_29": 0,
        "fg_missed_30_39": 0,
        "fg_missed_40_49": 0,
        "fg_missed_50_59": 0,
        "fg_missed_60_": 0,
        "fg_made_list": null,
        "fg_missed_list": null,
        "fg_blocked_list": null,
        "fg_made_distance": 0,
        "fg_missed_distance": 0,
        "fg_blocked_distance": 0,
        "pat_made": 0,
        "pat_att": 0,
        "pat_missed": 0,
        "pat_blocked": 0,
        "pat_pct": NaN,
        "gwfg_made": 0,
        "gwfg_att": 0,
        "gwfg_missed": 0,
        "gwfg_blocked": 0,
        "gwfg_distance": 0,
        "fantasy_points": 0.6000000000000001,
        "fantasy_points_ppr": 1.6
      },
      {
        "player_id": "00-0036364",
        "player_name": "L.Bowden",
        "player_display_name": "Lynn Bowden",
        "position": "WR",
        "position_group": "WR",
        "headshot_url": "https://static.www.nfl.com/image/private/f_auto,q_auto/league/nrvwudvuqxpmiegmjzdu",
        "season": 2023,
        "week": 18,
        "season_type": "REG",
        "team": "NO",
        "opponent_team": "ATL",
        "completions": 0,
        "attempts": 0,
        "passing_yards": 0,
        "passing_tds": 0,
        "passing_interceptions": 0,
        "sacks_suffered": 0,
        "sack_yards_lost": 0,
        "sack_fumbles": 0,
        "sack_fumbles_lost": 0,
        "passing_air_yards": 0,
        "passing_yards_after_catch": 0,
        "passing_first_downs": 0,
        "passing_epa": NaN,
        "passing_cpoe": NaN,
        "passing_2pt_conversions": 0,
        "pacr": NaN,
        "carries": 1,
        "rushing_yards": -2,
        "rushing_tds": 0,
        "rushing_fumbles": 1,
        "rushing_fumbles_lost": 0,
        "rushing_first_downs": 0,
        "rushing_epa": -1.004071738687344,
        "rushing_2pt_conversions": 0,
        "receptions": 1,
        "targets": 1,
        "receiving_yards": 5,
        "receiving_tds": 0,
        "receiving_fumbles": 0,
        "receiving_fumbles_lost": 0,
        "receiving_air_yards": -2,
        "receiving_yards_after_catch": 7,
        "receiving_first_downs": 0,
        "receiving_epa": -1.0067185712978244,
        "receiving_2pt_conversions": 0,
        "racr": 0.0,
        "target_share": 0.04,
        "air_yards_share": -0.008583690987124463,
        "wopr": 0.05399141630901287,
        "special_teams_tds": 0,
        "def_tackles_solo": 0,
        "def_tackles_with_assist": 0,
        "def_tackle_assists": 0,
        "def_tackles_for_loss": 0,
        "def_tackles_for_loss_yards": 0,
        "def_fumbles_forced": 0,
        "def_sacks": 0.0,
        "def_sack_yards": 0.0,
        "def_qb_hits": 0,
        "def_interceptions": 0,
        "def_interception_yards": 0,
        "def_pass_defended": 0,
        "def_tds": 0,
        "def_fumbles": 0,
        "def_safeties": 0,
        "misc_yards": 0,
        "fumble_recovery_own": 0,
        "fumble_recovery_yards_own": 0,
        "fumble_recovery_opp": 0,
        "fumble_recovery_yards_opp": 0,
        "fumble_recovery_tds": 0,
        "penalties": 0,
        "penalty_yards": 0,
        "punt_returns": 0,
        "punt_return_yards": 0,
        "kickoff_returns": 0,
        "kickoff_return_yards": 0,
        "fg_made": 0,
        "fg_att": 0,
        "fg_missed": 0,
        "fg_blocked": 0,
        "fg_long": NaN,
        "fg_pct": NaN,
        "fg_made_0_19": 0,
        "fg_made_20_29": 0,
        "fg_made_30_39": 0,
        "fg_made_40_49": 0,
        "fg_made_50_59": 0,
        "fg_made_60_": 0,
        "fg_missed_0_19": 0,
        "fg_missed_20_29": 0,
        "fg_missed_30_39": 0,
        "fg_missed_40_49": 0,
        "fg_missed_50_59": 0,
        "fg_missed_60_": 0,
        "fg_made_list": null,
        "fg_missed_list": null,
        "fg_blocked_list": null,
        "fg_made_distance": 0,
        "fg_missed_distance": 0,
        "fg_blocked_distance": 0,
        "pat_made": 0,
        "pat_att": 0,
        "pat_missed": 0,
        "pat_blocked": 0,
        "pat_pct": NaN,
        "gwfg_made": 0,
        "gwfg_att": 0,
        "gwfg_missed": 0,
        "gwfg_blocked": 0,
        "gwfg_distance": 0,
        "fantasy_points": 0.30000000000000004,
        "fantasy_points_ppr": 1.3
      }
    ],
    "sportradar": {}
  }
}