{
  "id": "espn:3915136",
  "fantasy": {
    "id": "espn:3915136",
    "name": "Jake Breeland",
    "position": null,
    "team": null,
    "identifiers": {
      "sleeper_id": null,
      "espn_id": "3915136",
      "gsis_id": null
    },
    "height": null,
    "weight": null,
    "college": null,
    "age": null,
    "years_exp": null,
    "birth_date": null
  },
  "nfl": {
    "bio": {
      "gsis_id": "00-0036154",
      "display_name": "Jacob Breeland",
      "common_first_name": "Jacob",
      "first_name": "Jacob",
      "last_name": "Breeland",
      "short_name": "J.Breeland",
      "football_name": "Jacob",
      "suffix": null,
      "esb_id": "BRE193434",
      "nfl_id": "53056",
      "pfr_id": "BreeJa01",
      "pff_id": "35748",
      "otc_id": null,
      "espn_id": "3915136",
      "smart_id": "32004252-4519-3434-7c5f-00fa76a0e7b9",
      "birth_date": "1996-09-20",
      "position_group": "TE",
      "position": "TE",
      "ngs_position_group": null,
      "ngs_position": null,
      "height": 77.0,
      "weight": 250.0,
      "headshot": "https://static.www.nfl.com/image/private/f_auto,q_auto/league/gea02itrsl3plfbnz0lb",
      "college_name": "Oregon",
      "college_conference": "Pacific Twelve Conference",
      "jersey_number": "0",
      "rookie_season": 2020,
      "last_season": 2020,
      "latest_team": "BAL",
      "status": "RSN",
      "ngs_status": "CUT",
      "ngs_status_short_description": "Waivers/No Rec.",
      "years_of_experience": 0,
      "pff_position": null,
      "pff_status": null,
      "draft_year": null,
      "draft_round": null,
      "draft_pick": null,
      "draft_team": null
    },
    "stats": [],
    "sportradar": {}
  }
}