{
  "id": "espn:4466",
  "fantasy": {
    "id": "espn:4466",
    "name": "Jordan Gross",
    "position": null,
    "team": null,
    "identifiers": {
      "sleeper_id": null,
      "espn_id": "4466",
      "gsis_id": null
    },
    "height": null,
    "weight": null,
    "college": null,
    "age": null,
    "years_exp": null,
    "birth_date": null
  },
  "nfl": {
    "bio": {
      "gsis_id": "00-0022117",
      "display_name": "Jordan Gross",
      "common_first_name": "Jordan",
      "first_name": "Jordan",
      "last_name": "Gross",
      "short_name": null,
      "football_name": null,
      "suffix": null,
      "esb_id": "GRO400181",
      "nfl_id": "28044",
      "pfr_id": "GrosJo20",
      "pff_id": "1324",
      "otc_id": "1176",
      "espn_id": "4466",
      "smart_id": "32004752-4f40-0181-5d7d-614876038a0d",
      "birth_date": "1980-07-20",
      "position_group": "OL",
      "position": "OT",
      "ngs_position_group": null,
      "ngs_position": null,
      "height": 76.0,
      "weight": 305.0,
      "headshot": "https://static.www.nfl.com/image/private/f_auto,q_auto/league/egv9hxbcu5ywrdfiazcv",
      "college_name": "Utah",
      "college_conference": null,
      "jersey_number": "69",
      "rookie_season": 2003,
      "last_season": 2013,
      "latest_team": "CAR",
      "status": "ACT",
      "ngs_status": null,
      "ngs_status_short_description": null,
      "years_of_experience": 11,
      "pff_position": "T",
      "pff_status": null,
      "draft_year": 2003.0,
      "draft_round": 1.0,
      "draft_pick": 8.0,
      "draft_team": "CAR"
    },
    "stats": [],
    "sportradar": {}
  }
}