{
  "id": "espn:1523",
  "fantasy": {
    "id": "espn:1523",
    "name": "Jeremy Brigham",
    "position": null,
    "team": null,
    "identifiers": {
      "sleeper_id": null,
      "espn_id": "1523",
      "gsis_id": null
    },
    "height": null,
    "weight": null,
    "college": null,
    "age": null,
    "years_exp": null,
    "birth_date": null
  },
  "nfl": {
    "bio": {
      "gsis_id": "00-0001766",
      "display_name": "Jeremy Brigham",
      "common_first_name": "Jeremy",
      "first_name": "Jeremy",
      "last_name": "Brigham",
      "short_name": null,
      "football_name": null,
      "suffix": null,
      "esb_id": "BRI260752",
      "nfl_id": "23575",
      "pfr_id": "BrigJe00",
      "pff_id": null,
      "otc_id": null,
      "espn_id": "1523",
      "smart_id": "32004252-4926-0752-9f69-c13552e7842f",
      "birth_date": "1975-03-22",
      "position_group": "TE",
      "position": "TE",
      "ngs_position_group": null,
      "ngs_position": null,
      "height": 78.0,
      "weight": 255.0,
      "headshot": "https://static.www.nfl.com/image/private/f_auto,q_auto/league/bcg9im99musloazyjzuo",
      "college_name": "Washington",
      "college_conference": null,
      "jersey_number": "87",
      "rookie_season": 1998,
      "last_season": 2002,
      "latest_team": "LV",
      "status": "ACT",
      "ngs_status": null,
      "ngs_status_short_description": null,
      "years_of_experience": 5,
      "pff_position": null,
      "pff_status": null,
      "draft_year": 1998.0,
      "draft_round": 5.0,
      "draft_pick": 127.0,
      "draft_team": "LV"
    },
    "stats": [],
    "sportradar": {}
  }
}