{
  "id": "espn:5405",
  "fantasy": {
    "id": "espn:5405",
    "name": "Joffrey Reynolds",
    "position": null,
    "team": null,
    "identifiers": {
      "sleeper_id": null,
      "espn_id": "5405",
      "gsis_id": null
    },
    "height": null,
    "weight": null,
    "college": null,
    "age": null,
    "years_exp": null,
    "birth_date": null
  },
  "nfl": {
    "bio": {
      "gsis_id": "00-0021431",
      "display_name": "Joffrey Reynolds",
      "common_first_name": "Joffrey",
      "first_name": "Joffrey",
      "last_name": "Reynolds",
      "short_name": null,
      "football_name": null,
      "suffix": null,
      "esb_id": "REY333749",
      "nfl_id": "28302",
      "pfr_id": "ReynJo20",
      "pff_id": null,
      "otc_id": null,
      "espn_id": "5405",
      "smart_id": "32005245-5933-3749-83a6-7818e41712fa",
      "birth_date": "1979-11-26",
      "position_group": "RB",
      "position": "RB",
      "ngs_position_group": null,
      "ngs_position": null,
      "height": 70.0,
      "weight": 221.0,
      "headshot": "https://static.www.nfl.com/image/private/f_auto,q_auto/league/uy58nyjsumq7hrwws0zq",
      "college_name": "Houston",
      "college_conference": null,
      "jersey_number": "26",
      "rookie_season": 2003,
      "last_season": 2003,
      "latest_team": "LA",
      "status": "CUT",
      "ngs_status": null,
      "ngs_status_short_description": null,
      "years_of_experience": 0,
      "pff_position": null,
      "pff_status": null,
      "draft_year": null,
      "draft_round": null,
      "draft_pick": null,
      "draft_team": null
    },
    "stats": [],
    "sportradar": {}
  }
}