{
  "id": "espn:7902",
  "fantasy": {
    "id": "espn:7902",
    "name": "Bobby Joe Edmonds",
    "position": null,
    "team": null,
    "identifiers": {
      "sleeper_id": null,
      "espn_id": "7902",
      "gsis_id": null
    },
    "height": null,
    "weight": null,
    "college": null,
    "age": null,
    "years_exp": null,
    "birth_date": null
  },
  "nfl": {
    "bio": {
      "gsis_id": "00-0004739",
      "display_name": "Bobby Joe Edmonds",
      "common_first_name": "Bobby Joe",
      "first_name": "Bobby",
      "last_name": "Edmonds",
      "short_name": null,
      "football_name": null,
      "suffix": null,
      "esb_id": "EDM166116",
      "nfl_id": null,
      "pfr_id": "EdmoBo00",
      "pff_id": null,
      "otc_id": null,
      "espn_id": "7902",
      "smart_id": "32004544-4d16-6116-43c8-4186e6cae6b8",
      "birth_date": "1964-09-26",
      "position_group": "RB",
      "position": "RB",
      "ngs_position_group": null,
      "ngs_position": null,
      "height": 71.0,
      "weight": 190.0,
      "headshot": "https://static.www.nfl.com/image/private/f_auto,q_auto/league/idctoo2tbzvtp7tcjokd",
      "college_name": "Arkansas",
      "college_conference": null,
      "jersey_number": "0",
      "rookie_season": 1986,
      "last_season": 1995,
      "latest_team": "TB",
      "status": "ACT",
      "ngs_status": null,
      "ngs_status_short_description": null,
      "years_of_experience": 5,
      "pff_position": null,
      "pff_status": null,
      "draft_year": 1986.0,
      "draft_round": 5.0,
      "draft_pick": 126.0,
      "draft_team": "SEA"
    },
    "stats": [],
    "sportradar": {}
  }
}