{
  "id": "espn:513",
  "fantasy": {
    "id": "espn:513",
    "name": "Darrin Smith",
    "position": null,
    "team": null,
    "identifiers": {
      "sleeper_id": null,
      "espn_id": "513",
      "gsis_id": null
    },
    "height": null,
    "weight": null,
    "college": null,
    "age": null,
    "years_exp": null,
    "birth_date": null
  },
  "nfl": {
    "bio": {
      "gsis_id": "00-0015132",
      "display_name": "Darrin Smith",
      "common_first_name": "Darrin",
      "first_name": "Darrin",
      "last_name": "Smith",
      "short_name": null,
      "football_name": null,
      "suffix": null,
      "esb_id": "SMI160080",
      "nfl_id": null,
      "pfr_id": "SmitDa22",
      "pff_id": null,
      "otc_id": null,
      "espn_id": "513",
      "smart_id": "3200534d-4916-0080-5320-03772c70748a",
      "birth_date": "1970-04-15",
      "position_group": "LB",
      "position": "LB",
      "ngs_position_group": null,
      "ngs_position": null,
      "height": 73.0,
      "weight": 236.0,
      "headshot": "https://static.www.nfl.com/image/private/f_auto,q_auto/league/ymgalcbqbpvyfiyrwu2n",
      "college_name": "Miami",
      "college_conference": null,
      "jersey_number": "54",
      "rookie_season": 1993,
      "last_season": 2004,
      "latest_team": "NO",
      "status": "ACT",
      "ngs_status": null,
      "ngs_status_short_description": null,
      "years_of_experience": 12,
      "pff_position": null,
      "pff_status": null,
      "draft_year": 1993.0,
      "draft_round": 2.0,
      "draft_pick": 54.0,
      "draft_team": "DAL"
    },
    "stats": [],
    "sportradar": {}
  }
}