{
  "id": "espn:7669",
  "fantasy": {
    "id": "espn:7669",
    "name": "Dexter Nottage",
    "position": null,
    "team": null,
    "identifiers": {
      "sleeper_id": null,
      "espn_id": "7669",
      "gsis_id": null
    },
    "height": null,
    "weight": null,
    "college": null,
    "age": null,
    "years_exp": null,
    "birth_date": null
  },
  "nfl": {
    "bio": {
      "gsis_id": "00-0012205",
      "display_name": "Dexter Nottage",
      "common_first_name": "Dexter",
      "first_name": "Dexter",
      "last_name": "Nottage",
      "short_name": null,
      "football_name": null,
      "suffix": null,
      "esb_id": "NOT438361",
      "nfl_id": null,
      "pfr_id": "NottDe20",
      "pff_id": null,
      "otc_id": null,
      "espn_id": "7669",
      "smart_id": "32004e4f-5443-8361-6ba5-8f81f24a1bbb",
      "birth_date": "1970-11-14",
      "position_group": "DL",
      "position": "DE",
      "ngs_position_group": null,
      "ngs_position": null,
      "height": 76.0,
      "weight": 287.0,
      "headshot": "https://static.www.nfl.com/image/private/f_auto,q_auto/league/vtjewpmgdnhjpfbj5hmv",
      "college_name": "Florida A&M",
      "college_conference": null,
      "jersey_number": "94",
      "rookie_season": 1994,
      "last_season": 1997,
      "latest_team": "KC",
      "status": "CUT",
      "ngs_status": null,
      "ngs_status_short_description": null,
      "years_of_experience": 4,
      "pff_position": null,
      "pff_status": null,
      "draft_year": 1994.0,
      "draft_round": 6.0,
      "draft_pick": 163.0,
      "draft_team": "WAS"
    },
    "stats": [],
    "sportradar": {}
  }
}